{"id":"1996","title":"Captain America (1968 - 1996)","description":"The Star-Spangled Avenger fights for freedom! Emerging from years on ice following World War II, Steve Rogers must adapt to a world that has gone on without him while also protecting his nation from the forces that would conspire to tear it apart!","resourceURI":"http://gateway.marvel.com/v1/public/series/1996","startYear":1968,"endYear":1996,"thumbnail":"http://i.annihil.us/u/prod/marvel/i/mg/2/50/5130f2104b29a/portrait_medium.jpg","issueCount":355,"issues":[{"id":7835,"title":"Captain America (1968) #454","issueNumber":454.0,"resourceURI":"http://gateway.marvel.com/v1/public/comics/7835","date":"1996-08-10T00:00:00-0400","price":0.0,"thumbnail":"http://i.annihil.us/u/prod/marvel/i/mg/1/a0/51d2ebb6ccaa6/portrait_medium.jpg"},{"id":7834,"title":"Captain America (1968) #453","issueNumber":453.0,"resourceURI":"http://gateway.marvel.com/v1/public/comics/7834","date":"1996-07-10T00:00:00-0400","price":0.0,"thumbnail":"http://i.annihil.us/u/prod/marvel/i/mg/2/c0/4d2504226ac82/portrait_medium.jpg"},{"id":7833,"title":"Captain America (1968) #452","issueNumber":452.0,"resourceURI":"http://gateway.marvel.com/v1/public/comics/7833","date":"1996-06-10T00:00:00-0400","price":0.0,"thumbnail":"http://i.annihil.us/u/prod/marvel/i/mg/e/90/51d2ebcba3c36/portrait_medium.jpg"},{"id":7832,"title":"Captain America (1968) #451","issueNumber":451.0,"resourceURI":"http://gateway.marvel.com/v1/public/comics/7832","date":"1996-05-10T00:00:00-0400","price":0.0,"thumbnail":"http://i.annihil.us/u/prod/marvel/i/mg/9/20/51d2ea7fd3362/portrait_medium.jpg"},{"id":7831,"title":"Captain America (1968) #450","issueNumber":450.0,"resourceURI":"http://gateway.marvel.com/v1/public/comics/7831","date":"1996-04-10T00:00:00-0400","price":0.0,"thumbnail":"http://i.annihil.us/u/prod/marvel/i/mg/6/a0/51d2ea949861b/portrait_medium.jpg"},{"id":7830,"title":"Captain America (1968) #449","issueNumber":449.0,"resourceURI":"http://gateway.marvel.com/v1/public/comics/7830","date":"1996-03-10T00:00:00-0500","price":0.0,"thumbnail":"http://i.annihil.us/u/prod/marvel/i/mg/d/70/51ed98d59f7fa/portrait_medium.jpg"},{"id":7829,"title":"Captain America (1968) #448","issueNumber":448.0,"resourceURI":"http://gateway.marvel.com/v1/public/comics/7829","date":"1996-02-10T00:00:00-0500","price":0.0,"thumbnail":"http://i.annihil.us/u/prod/marvel/i/mg/c/d0/51d2ea8e7d8e5/portrait_medium.jpg"},{"id":7828,"title":"Captain America (1968) #447","issueNumber":447.0,"resourceURI":"http://gateway.marvel.com/v1/public/comics/7828","date":"1996-01-10T00:00:00-0500","price":0.0,"thumbnail":"http://i.annihil.us/u/prod/marvel/i/mg/e/90/51d2e9b24baab/portrait_medium.jpg"},{"id":7827,"title":"Captain America (1968) #446","issueNumber":446.0,"resourceURI":"http://gateway.marvel.com/v1/public/comics/7827","date":"1995-12-10T00:00:00-0500","price":0.0,"thumbnail":"http://i.annihil.us/u/prod/marvel/i/mg/5/e0/51d2e9c23343a/portrait_medium.jpg"},{"id":7826,"title":"Captain America (1968) #445","issueNumber":445.0,"resourceURI":"http://gateway.marvel.com/v1/public/comics/7826","date":"1995-11-10T00:00:00-0500","price":0.0,"thumbnail":"http://i.annihil.us/u/prod/marvel/i/mg/3/a0/51d2e9c406774/portrait_medium.jpg"},{"id":7825,"title":"Captain America (1968) #444","issueNumber":444.0,"resourceURI":"http://gateway.marvel.com/v1/public/comics/7825","date":"1995-10-10T00:00:00-0400","price":0.0,"thumbnail":"http://i.annihil.us/u/prod/marvel/i/mg/4/00/51d2e9d269817/portrait_medium.jpg"},{"id":7824,"title":"Captain America (1968) #443","issueNumber":443.0,"resourceURI":"http://gateway.marvel.com/v1/public/comics/7824","date":"1995-09-10T00:00:00-0400","price":0.0,"thumbnail":"http://i.annihil.us/u/prod/marvel/i/mg/7/50/5239d798a27ef/portrait_medium.jpg"},{"id":7823,"title":"Captain America (1968) #442","issueNumber":442.0,"resourceURI":"http://gateway.marvel.com/v1/public/comics/7823","date":"1995-08-10T00:00:00-0400","price":0.0,"thumbnail":"http://i.annihil.us/u/prod/marvel/i/mg/4/00/5239dfc667741/portrait_medium.jpg"},{"id":7822,"title":"Captain America (1968) #441","issueNumber":441.0,"resourceURI":"http://gateway.marvel.com/v1/public/comics/7822","date":"1995-07-10T00:00:00-0400","price":0.0,"thumbnail":"http://i.annihil.us/u/prod/marvel/i/mg/9/50/5229ffb054cc5/portrait_medium.jpg"},{"id":7821,"title":"Captain America (1968) #440","issueNumber":440.0,"resourceURI":"http://gateway.marvel.com/v1/public/comics/7821","date":"1995-06-10T00:00:00-0400","price":0.0,"thumbnail":"http://i.annihil.us/u/prod/marvel/i/mg/2/40/5229ffea3ceac/portrait_medium.jpg"},{"id":7820,"title":"Captain America (1968) #439","issueNumber":439.0,"resourceURI":"http://gateway.marvel.com/v1/public/comics/7820","date":"1995-05-10T00:00:00-0400","price":0.0,"thumbnail":"http://i.annihil.us/u/prod/marvel/i/mg/2/a0/5239e00540fa1/portrait_medium.jpg"},{"id":7819,"title":"Captain America (1968) #438","issueNumber":438.0,"resourceURI":"http://gateway.marvel.com/v1/public/comics/7819","date":"1995-04-10T00:00:00-0400","price":0.0,"thumbnail":"http://i.annihil.us/u/prod/marvel/i/mg/6/03/5239d1b774180/portrait_medium.jpg"},{"id":7818,"title":"Captain America (1968) #437","issueNumber":437.0,"resourceURI":"http://gateway.marvel.com/v1/public/comics/7818","date":"1995-03-10T00:00:00-0500","price":0.0,"thumbnail":"http://i.annihil.us/u/prod/marvel/i/mg/9/a0/4d9483ce0e34e/portrait_medium.jpg"},{"id":7817,"title":"Captain America (1968) #436","issueNumber":436.0,"resourceURI":"http://gateway.marvel.com/v1/public/comics/7817","date":"1995-02-10T00:00:00-0500","price":0.0,"thumbnail":"http://i.annihil.us/u/prod/marvel/i/mg/7/03/4d948360a2067/portrait_medium.jpg"},{"id":7816,"title":"Captain America (1968) #435","issueNumber":435.0,"resourceURI":"http://gateway.marvel.com/v1/public/comics/7816","date":"1995-01-10T00:00:00-0500","price":0.0,"thumbnail":"http://i.annihil.us/u/prod/marvel/i/mg/d/70/4d9482fed8f6d/portrait_medium.jpg"},{"id":7815,"title":"Captain America (1968) #434","issueNumber":434.0,"resourceURI":"http://gateway.marvel.com/v1/public/comics/7815","date":"1994-12-10T00:00:00-0500","price":0.0,"thumbnail":"http://i.annihil.us/u/prod/marvel/i/mg/7/20/4d9482a92eb96/portrait_medium.jpg"},{"id":7814,"title":"Captain America (1968) #433","issueNumber":433.0,"resourceURI":"http://gateway.marvel.com/v1/public/comics/7814","date":"1994-11-10T00:00:00-0500","price":0.0,"thumbnail":"http://i.annihil.us/u/prod/marvel/i/mg/6/a0/4d94824eab941/portrait_medium.jpg"},{"id":7813,"title":"Captain America (1968) #432","issueNumber":432.0,"resourceURI":"http://gateway.marvel.com/v1/public/comics/7813","date":"1994-10-10T00:00:00-0400","price":0.0,"thumbnail":"http://i.annihil.us/u/prod/marvel/i/mg/2/e0/4d9482005eb11/portrait_medium.jpg"},{"id":7812,"title":"Captain America (1968) #431","issueNumber":431.0,"resourceURI":"http://gateway.marvel.com/v1/public/comics/7812","date":"1994-09-10T00:00:00-0400","price":0.0,"thumbnail":"http://i.annihil.us/u/prod/marvel/i/mg/4/40/4d948156dc991/portrait_medium.jpg"},{"id":7811,"title":"Captain America (1968) #430","issueNumber":430.0,"resourceURI":"http://gateway.marvel.com/v1/public/comics/7811","date":"1994-08-10T00:00:00-0400","price":0.0,"thumbnail":"http://i.annihil.us/u/prod/marvel/i/mg/b/d0/50b3f16f5dad1/portrait_medium.jpg"},{"id":7810,"title":"Captain America (1968) #429","issueNumber":429.0,"resourceURI":"http://gateway.marvel.com/v1/public/comics/7810","date":"1994-07-10T00:00:00-0400","price":0.0,"thumbnail":"http://i.annihil.us/u/prod/marvel/i/mg/8/d0/50b3f214deb64/portrait_medium.jpg"},{"id":7809,"title":"Captain America (1968) #428","issueNumber":428.0,"resourceURI":"http://gateway.marvel.com/v1/public/comics/7809","date":"1994-06-10T00:00:00-0400","price":0.0,"thumbnail":"http://i.annihil.us/u/prod/marvel/i/mg/2/70/50b3f30b91241/portrait_medium.jpg"},{"id":7808,"title":"Captain America (1968) #427","issueNumber":427.0,"resourceURI":"http://gateway.marvel.com/v1/public/comics/7808","date":"1994-05-10T00:00:00-0400","price":0.0,"thumbnail":"http://i.annihil.us/u/prod/marvel/i/mg/9/40/50b3f3d77a2f5/portrait_medium.jpg"},{"id":7807,"title":"Captain America (1968) #426","issueNumber":426.0,"resourceURI":"http://gateway.marvel.com/v1/public/comics/7807","date":"1994-04-10T00:00:00-0400","price":0.0,"thumbnail":"http://i.annihil.us/u/prod/marvel/i/mg/6/00/50b3f417d046e/portrait_medium.jpg"},{"id":7806,"title":"Captain America (1968) #425","issueNumber":425.0,"resourceURI":"http://gateway.marvel.com/v1/public/comics/7806","date":"1994-03-10T00:00:00-0500","price":0.0,"thumbnail":"http://i.annihil.us/u/prod/marvel/i/mg/c/10/50b3f8d30c5cf/portrait_medium.jpg"},{"id":7805,"title":"Captain America (1968) #424","issueNumber":424.0,"resourceURI":"http://gateway.marvel.com/v1/public/comics/7805","date":"1994-02-10T00:00:00-0500","price":0.0,"thumbnail":"http://i.annihil.us/u/prod/marvel/i/mg/1/30/5239c988c0862/portrait_medium.jpg"},{"id":7804,"title":"Captain America (1968) #423","issueNumber":423.0,"resourceURI":"http://gateway.marvel.com/v1/public/comics/7804","date":"1994-01-10T00:00:00-0500","price":0.0,"thumbnail":"http://i.annihil.us/u/prod/marvel/i/mg/6/c0/52615eef767d0/portrait_medium.jpg"},{"id":7803,"title":"Captain America (1968) #422","issueNumber":422.0,"resourceURI":"http://gateway.marvel.com/v1/public/comics/7803","date":"1993-12-10T00:00:00-0500","price":0.0,"thumbnail":"http://i.annihil.us/u/prod/marvel/i/mg/7/10/5294e75906ccf/portrait_medium.jpg"},{"id":7802,"title":"Captain America (1968) #421","issueNumber":421.0,"resourceURI":"http://gateway.marvel.com/v1/public/comics/7802","date":"1993-11-10T00:00:00-0500","price":0.0,"thumbnail":"http://i.annihil.us/u/prod/marvel/i/mg/2/e0/5230b92c0a477/portrait_medium.jpg"},{"id":7801,"title":"Captain America (1968) #420","issueNumber":420.0,"resourceURI":"http://gateway.marvel.com/v1/public/comics/7801","date":"1993-10-10T00:00:00-0400","price":0.0,"thumbnail":"http://i.annihil.us/u/prod/marvel/i/mg/c/03/59c0128c85834/portrait_medium.jpg"},{"id":7800,"title":"Captain America (1968) #419","issueNumber":419.0,"resourceURI":"http://gateway.marvel.com/v1/public/comics/7800","date":"1993-09-10T00:00:00-0400","price":0.0,"thumbnail":"http://i.annihil.us/u/prod/marvel/i/mg/3/10/59c01152bf185/portrait_medium.jpg"},{"id":7799,"title":"Captain America (1968) #418","issueNumber":418.0,"resourceURI":"http://gateway.marvel.com/v1/public/comics/7799","date":"1993-08-10T00:00:00-0400","price":0.0,"thumbnail":"http://i.annihil.us/u/prod/marvel/i/mg/f/c0/59c01011554d5/portrait_medium.jpg"},{"id":7798,"title":"Captain America (1968) #417","issueNumber":417.0,"resourceURI":"http://gateway.marvel.com/v1/public/comics/7798","date":"1993-07-10T00:00:00-0400","price":0.0,"thumbnail":"http://i.annihil.us/u/prod/marvel/i/mg/f/10/59c00eaecce90/portrait_medium.jpg"},{"id":7797,"title":"Captain America (1968) #416","issueNumber":416.0,"resourceURI":"http://gateway.marvel.com/v1/public/comics/7797","date":"1993-06-10T00:00:00-0400","price":0.0,"thumbnail":"http://i.annihil.us/u/prod/marvel/i/mg/3/60/59c00d77c5631/portrait_medium.jpg"},{"id":7796,"title":"Captain America (1968) #415","issueNumber":415.0,"resourceURI":"http://gateway.marvel.com/v1/public/comics/7796","date":"1993-05-10T00:00:00-0400","price":0.0,"thumbnail":"http://i.annihil.us/u/prod/marvel/i/mg/8/e0/59c00c1d0ed47/portrait_medium.jpg"},{"id":7795,"title":"Captain America (1968) #414","issueNumber":414.0,"resourceURI":"http://gateway.marvel.com/v1/public/comics/7795","date":"1993-04-10T00:00:00-0400","price":0.0,"thumbnail":"http://i.annihil.us/u/prod/marvel/i/mg/a/40/59bffb282c877/portrait_medium.jpg"},{"id":7794,"title":"Captain America (1968) #413","issueNumber":413.0,"resourceURI":"http://gateway.marvel.com/v1/public/comics/7794","date":"1993-03-10T00:00:00-0500","price":0.0,"thumbnail":"http://i.annihil.us/u/prod/marvel/i/mg/d/00/59bff97b0cb75/portrait_medium.jpg"},{"id":7793,"title":"Captain America (1968) #412","issueNumber":412.0,"resourceURI":"http://gateway.marvel.com/v1/public/comics/7793","date":"1993-02-10T00:00:00-0500","price":0.0,"thumbnail":"http://i.annihil.us/u/prod/marvel/i/mg/c/50/59bff74112fba/portrait_medium.jpg"},{"id":7792,"title":"Captain America (1968) #411","issueNumber":411.0,"resourceURI":"http://gateway.marvel.com/v1/public/comics/7792","date":"1993-01-10T00:00:00-0500","price":0.0,"thumbnail":"http://i.annihil.us/u/prod/marvel/i/mg/6/e0/59bff55501a79/portrait_medium.jpg"},{"id":7791,"title":"Captain America (1968) #410","issueNumber":410.0,"resourceURI":"http://gateway.marvel.com/v1/public/comics/7791","date":"1992-12-10T00:00:00-0500","price":0.0,"thumbnail":"http://i.annihil.us/u/prod/marvel/i/mg/4/00/5294ed17e1695/portrait_medium.jpg"},{"id":7790,"title":"Captain America (1968) #409","issueNumber":409.0,"resourceURI":"http://gateway.marvel.com/v1/public/comics/7790","date":"1992-11-10T00:00:00-0500","price":0.0,"thumbnail":"http://i.annihil.us/u/prod/marvel/i/mg/7/80/5294ed83919ff/portrait_medium.jpg"},{"id":7789,"title":"Captain America (1968) #408","issueNumber":408.0,"resourceURI":"http://gateway.marvel.com/v1/public/comics/7789","date":"1992-10-10T00:00:00-0400","price":0.0,"thumbnail":"http://i.annihil.us/u/prod/marvel/i/mg/5/20/50ac210125cc7/portrait_medium.jpg"},{"id":7788,"title":"Captain America (1968) #407","issueNumber":407.0,"resourceURI":"http://gateway.marvel.com/v1/public/comics/7788","date":"1992-09-20T00:00:00-0400","price":0.0,"thumbnail":"http://i.annihil.us/u/prod/marvel/i/mg/5/80/50ac2183c0d81/portrait_medium.jpg"},{"id":7787,"title":"Captain America (1968) #406","issueNumber":406.0,"resourceURI":"http://gateway.marvel.com/v1/public/comics/7787","date":"1992-09-10T00:00:00-0400","price":0.0,"thumbnail":"http://i.annihil.us/u/prod/marvel/i/mg/5/e0/50ac21c5d3738/portrait_medium.jpg"},{"id":7786,"title":"Captain America (1968) #405","issueNumber":405.0,"resourceURI":"http://gateway.marvel.com/v1/public/comics/7786","date":"1992-08-20T00:00:00-0400","price":0.0,"thumbnail":"http://i.annihil.us/u/prod/marvel/i/mg/9/10/50acf450b99c1/portrait_medium.jpg"},{"id":7785,"title":"Captain America (1968) #404","issueNumber":404.0,"resourceURI":"http://gateway.marvel.com/v1/public/comics/7785","date":"1992-08-10T00:00:00-0400","price":0.0,"thumbnail":"http://i.annihil.us/u/prod/marvel/i/mg/2/00/50acf4fb3eed3/portrait_medium.jpg"},{"id":7784,"title":"Captain America (1968) #403","issueNumber":403.0,"resourceURI":"http://gateway.marvel.com/v1/public/comics/7784","date":"1992-07-20T00:00:00-0400","price":0.0,"thumbnail":"http://i.annihil.us/u/prod/marvel/i/mg/c/20/50b3feaa8e058/portrait_medium.jpg"},{"id":7783,"title":"Captain America (1968) #402","issueNumber":402.0,"resourceURI":"http://gateway.marvel.com/v1/public/comics/7783","date":"1992-07-10T00:00:00-0400","price":0.0,"thumbnail":"http://i.annihil.us/u/prod/marvel/i/mg/6/30/50acf5f842703/portrait_medium.jpg"},{"id":7782,"title":"Captain America (1968) #401","issueNumber":401.0,"resourceURI":"http://gateway.marvel.com/v1/public/comics/7782","date":"1992-06-10T00:00:00-0400","price":0.0,"thumbnail":"http://i.annihil.us/u/prod/marvel/i/mg/c/40/4bb6ee3c875a0/portrait_medium.jpg"},{"id":7781,"title":"Captain America (1968) #400","issueNumber":400.0,"resourceURI":"http://gateway.marvel.com/v1/public/comics/7781","date":"1992-05-10T00:00:00-0400","price":0.0,"thumbnail":"http://i.annihil.us/u/prod/marvel/i/mg/9/a0/56e6e0d39e71a/portrait_medium.jpg"},{"id":7780,"title":"Captain America (1968) #399","issueNumber":399.0,"resourceURI":"http://gateway.marvel.com/v1/public/comics/7780","date":"1992-04-10T00:00:00-0400","price":0.0,"thumbnail":"http://i.annihil.us/u/prod/marvel/i/mg/2/20/4bb6ee41c9ccb/portrait_medium.jpg"},{"id":7779,"title":"Captain America (1968) #398","issueNumber":398.0,"resourceURI":"http://gateway.marvel.com/v1/public/comics/7779","date":"1992-03-10T00:00:00-0500","price":0.0,"thumbnail":"http://i.annihil.us/u/prod/marvel/i/mg/f/90/56e6e03aeea8f/portrait_medium.jpg"},{"id":7778,"title":"Captain America (1968) #397","issueNumber":397.0,"resourceURI":"http://gateway.marvel.com/v1/public/comics/7778","date":"1992-02-10T00:00:00-0500","price":0.0,"thumbnail":"http://i.annihil.us/u/prod/marvel/i/mg/3/e0/5294f435ed617/portrait_medium.jpg"},{"id":7777,"title":"Captain America (1968) #396","issueNumber":396.0,"resourceURI":"http://gateway.marvel.com/v1/public/comics/7777","date":"1992-01-10T00:00:00-0500","price":0.0,"thumbnail":"http://i.annihil.us/u/prod/marvel/i/mg/9/d0/5294f4a65d3fe/portrait_medium.jpg"},{"id":7776,"title":"Captain America (1968) #395","issueNumber":395.0,"resourceURI":"http://gateway.marvel.com/v1/public/comics/7776","date":"1991-12-10T00:00:00-0500","price":0.0,"thumbnail":"http://i.annihil.us/u/prod/marvel/i/mg/b/b0/521f65a03cfac/portrait_medium.jpg"},{"id":7775,"title":"Captain America (1968) #394","issueNumber":394.0,"resourceURI":"http://gateway.marvel.com/v1/public/comics/7775","date":"1991-11-10T00:00:00-0500","price":0.0,"thumbnail":"http://i.annihil.us/u/prod/marvel/i/mg/6/70/5294f4dc725a2/portrait_medium.jpg"},{"id":7774,"title":"Captain America (1968) #393","issueNumber":393.0,"resourceURI":"http://gateway.marvel.com/v1/public/comics/7774","date":"1991-10-10T00:00:00-0400","price":0.0,"thumbnail":"http://i.annihil.us/u/prod/marvel/i/mg/4/90/5294f50c987f8/portrait_medium.jpg"},{"id":7773,"title":"Captain America (1968) #392","issueNumber":392.0,"resourceURI":"http://gateway.marvel.com/v1/public/comics/7773","date":"1991-09-20T00:00:00-0400","price":0.0,"thumbnail":"http://i.annihil.us/u/prod/marvel/i/mg/3/20/5294f5416cb20/portrait_medium.jpg"},{"id":7772,"title":"Captain America (1968) #391","issueNumber":391.0,"resourceURI":"http://gateway.marvel.com/v1/public/comics/7772","date":"1991-09-10T00:00:00-0400","price":0.0,"thumbnail":"http://i.annihil.us/u/prod/marvel/i/mg/1/60/5294f577366e4/portrait_medium.jpg"},{"id":7771,"title":"Captain America (1968) #390","issueNumber":390.0,"resourceURI":"http://gateway.marvel.com/v1/public/comics/7771","date":"1991-08-20T00:00:00-0400","price":0.0,"thumbnail":"http://i.annihil.us/u/prod/marvel/i/mg/6/80/5294f5dd233c5/portrait_medium.jpg"},{"id":7770,"title":"Captain America (1968) #389","issueNumber":389.0,"resourceURI":"http://gateway.marvel.com/v1/public/comics/7770","date":"1991-08-10T00:00:00-0400","price":0.0,"thumbnail":"http://i.annihil.us/u/prod/marvel/i/mg/f/03/5294f60f05676/portrait_medium.jpg"},{"id":7769,"title":"Captain America (1968) #388","issueNumber":388.0,"resourceURI":"http://gateway.marvel.com/v1/public/comics/7769","date":"1991-07-20T00:00:00-0400","price":0.0,"thumbnail":"http://i.annihil.us/u/prod/marvel/i/mg/4/20/5294f641587bf/portrait_medium.jpg"},{"id":7768,"title":"Captain America (1968) #387","issueNumber":387.0,"resourceURI":"http://gateway.marvel.com/v1/public/comics/7768","date":"1991-07-10T00:00:00-0400","price":0.0,"thumbnail":"http://i.annihil.us/u/prod/marvel/i/mg/e/50/5294f67144389/portrait_medium.jpg"},{"id":7767,"title":"Captain America (1968) #386","issueNumber":386.0,"resourceURI":"http://gateway.marvel.com/v1/public/comics/7767","date":"1991-06-10T00:00:00-0400","price":0.0,"thumbnail":"http://i.annihil.us/u/prod/marvel/i/mg/6/80/5294f6a3e165b/portrait_medium.jpg"},{"id":7766,"title":"Captain America (1968) #385","issueNumber":385.0,"resourceURI":"http://gateway.marvel.com/v1/public/comics/7766","date":"1991-05-10T00:00:00-0400","price":0.0,"thumbnail":"http://i.annihil.us/u/prod/marvel/i/mg/4/20/5294f93935b4d/portrait_medium.jpg"},{"id":7765,"title":"Captain America (1968) #384","issueNumber":384.0,"resourceURI":"http://gateway.marvel.com/v1/public/comics/7765","date":"1991-04-10T00:00:00-0400","price":0.0,"thumbnail":"http://i.annihil.us/u/prod/marvel/i/mg/c/03/5294f96f12027/portrait_medium.jpg"},{"id":7764,"title":"Captain America (1968) #383","issueNumber":383.0,"resourceURI":"http://gateway.marvel.com/v1/public/comics/7764","date":"1991-03-10T00:00:00-0500","price":0.0,"thumbnail":"http://i.annihil.us/u/prod/marvel/i/mg/7/80/5266c6ee8f955/portrait_medium.jpg"},{"id":7763,"title":"Captain America (1968) #382","issueNumber":382.0,"resourceURI":"http://gateway.marvel.com/v1/public/comics/7763","date":"1991-02-10T00:00:00-0500","price":0.0,"thumbnail":"http://i.annihil.us/u/prod/marvel/i/mg/c/00/521b7f2e43ccd/portrait_medium.jpg"},{"id":7762,"title":"Captain America (1968) #381","issueNumber":381.0,"resourceURI":"http://gateway.marvel.com/v1/public/comics/7762","date":"1991-01-10T00:00:00-0500","price":0.0,"thumbnail":"http://i.annihil.us/u/prod/marvel/i/mg/2/f0/521b711c7338c/portrait_medium.jpg"},{"id":7761,"title":"Captain America (1968) #380","issueNumber":380.0,"resourceURI":"http://gateway.marvel.com/v1/public/comics/7761","date":"1990-12-10T00:00:00-0500","price":0.0,"thumbnail":"http://i.annihil.us/u/prod/marvel/i/mg/6/40/5214ed9723ab6/portrait_medium.jpg"},{"id":7760,"title":"Captain America (1968) #379","issueNumber":379.0,"resourceURI":"http://gateway.marvel.com/v1/public/comics/7760","date":"1990-11-10T00:00:00-0500","price":0.0,"thumbnail":"http://i.annihil.us/u/prod/marvel/i/mg/7/30/5294f9a18b9a9/portrait_medium.jpg"},{"id":7759,"title":"Captain America (1968) #378","issueNumber":378.0,"resourceURI":"http://gateway.marvel.com/v1/public/comics/7759","date":"1990-10-10T00:00:00-0400","price":0.0,"thumbnail":"http://i.annihil.us/u/prod/marvel/i/mg/6/f0/5294f9d5106fe/portrait_medium.jpg"},{"id":7758,"title":"Captain America (1968) #377","issueNumber":377.0,"resourceURI":"http://gateway.marvel.com/v1/public/comics/7758","date":"1990-09-20T00:00:00-0400","price":0.0,"thumbnail":"http://i.annihil.us/u/prod/marvel/i/mg/5/f0/5214e7af0228c/portrait_medium.jpg"},{"id":7757,"title":"Captain America (1968) #376","issueNumber":376.0,"resourceURI":"http://gateway.marvel.com/v1/public/comics/7757","date":"1990-09-10T00:00:00-0400","price":0.0,"thumbnail":"http://i.annihil.us/u/prod/marvel/i/mg/9/a0/5266a4f098bfb/portrait_medium.jpg"},{"id":7756,"title":"Captain America (1968) #375","issueNumber":375.0,"resourceURI":"http://gateway.marvel.com/v1/public/comics/7756","date":"1990-08-20T00:00:00-0400","price":0.0,"thumbnail":"http://i.annihil.us/u/prod/marvel/i/mg/4/03/5266a52d28703/portrait_medium.jpg"},{"id":7755,"title":"Captain America (1968) #374","issueNumber":374.0,"resourceURI":"http://gateway.marvel.com/v1/public/comics/7755","date":"1990-08-10T00:00:00-0400","price":0.0,"thumbnail":"http://i.annihil.us/u/prod/marvel/i/mg/6/50/5266a567e0cf0/portrait_medium.jpg"},{"id":7754,"title":"Captain America (1968) #373","issueNumber":373.0,"resourceURI":"http://gateway.marvel.com/v1/public/comics/7754","date":"1990-07-20T00:00:00-0400","price":0.0,"thumbnail":"http://i.annihil.us/u/prod/marvel/i/mg/2/d0/5266a5a46c122/portrait_medium.jpg"},{"id":7753,"title":"Captain America (1968) #372","issueNumber":372.0,"resourceURI":"http://gateway.marvel.com/v1/public/comics/7753","date":"1990-07-10T00:00:00-0400","price":0.0,"thumbnail":"http://i.annihil.us/u/prod/marvel/i/mg/3/d0/521b68e5d3199/portrait_medium.jpg"},{"id":7752,"title":"Captain America (1968) #371","issueNumber":371.0,"resourceURI":"http://gateway.marvel.com/v1/public/comics/7752","date":"1990-06-10T00:00:00-0400","price":0.0,"thumbnail":"http://i.annihil.us/u/prod/marvel/i/mg/4/70/52669cb4677e8/portrait_medium.jpg"},{"id":7751,"title":"Captain America (1968) #370","issueNumber":370.0,"resourceURI":"http://gateway.marvel.com/v1/public/comics/7751","date":"1990-05-10T00:00:00-0400","price":0.0,"thumbnail":"http://i.annihil.us/u/prod/marvel/i/mg/a/20/56e6df934c9c2/portrait_medium.jpg"},{"id":7750,"title":"Captain America (1968) #369","issueNumber":369.0,"resourceURI":"http://gateway.marvel.com/v1/public/comics/7750","date":"1990-04-10T00:00:00-0400","price":0.0,"thumbnail":"http://i.annihil.us/u/prod/marvel/i/mg/9/c0/52669ced7ba27/portrait_medium.jpg"},{"id":7749,"title":"Captain America (1968) #368","issueNumber":368.0,"resourceURI":"http://gateway.marvel.com/v1/public/comics/7749","date":"1990-03-10T00:00:00-0500","price":0.0,"thumbnail":"http://i.annihil.us/u/prod/marvel/i/mg/7/30/526696de2e94c/portrait_medium.jpg"},{"id":7748,"title":"Captain America (1968) #367","issueNumber":367.0,"resourceURI":"http://gateway.marvel.com/v1/public/comics/7748","date":"1990-02-10T00:00:00-0500","price":0.0,"thumbnail":"http://i.annihil.us/u/prod/marvel/i/mg/2/90/5193b4a22a118/portrait_medium.jpg"},{"id":7747,"title":"Captain America (1968) #366","issueNumber":366.0,"resourceURI":"http://gateway.marvel.com/v1/public/comics/7747","date":"1990-01-10T00:00:00-0500","price":0.0,"thumbnail":"http://i.annihil.us/u/prod/marvel/i/mg/9/80/5193ac6d9c34d/portrait_medium.jpg"},{"id":7746,"title":"Captain America (1968) #365","issueNumber":365.0,"resourceURI":"http://gateway.marvel.com/v1/public/comics/7746","date":"1989-12-20T00:00:00-0500","price":0.0,"thumbnail":"http://i.annihil.us/u/prod/marvel/i/mg/7/03/5193a691817c0/portrait_medium.jpg"},{"id":7745,"title":"Captain America (1968) #364","issueNumber":364.0,"resourceURI":"http://gateway.marvel.com/v1/public/comics/7745","date":"1989-12-10T00:00:00-0500","price":0.0,"thumbnail":"http://i.annihil.us/u/prod/marvel/i/mg/8/f0/59a6f6ca017a0/portrait_medium.jpg"},{"id":7744,"title":"Captain America (1968) #363","issueNumber":363.0,"resourceURI":"http://gateway.marvel.com/v1/public/comics/7744","date":"1989-11-30T00:00:00-0500","price":0.0,"thumbnail":"http://i.annihil.us/u/prod/marvel/i/mg/9/a0/59a6e3b278bc4/portrait_medium.jpg"},{"id":7743,"title":"Captain America (1968) #362","issueNumber":362.0,"resourceURI":"http://gateway.marvel.com/v1/public/comics/7743","date":"1989-11-20T00:00:00-0500","price":0.0,"thumbnail":"http://i.annihil.us/u/prod/marvel/i/mg/7/00/4f20779a8c6a9/portrait_medium.jpg"},{"id":7742,"title":"Captain America (1968) #361","issueNumber":361.0,"resourceURI":"http://gateway.marvel.com/v1/public/comics/7742","date":"1989-11-10T00:00:00-0500","price":0.0,"thumbnail":"http://i.annihil.us/u/prod/marvel/i/mg/9/30/4f2071fb51f8b/portrait_medium.jpg"},{"id":7741,"title":"Captain America (1968) #360","issueNumber":360.0,"resourceURI":"http://gateway.marvel.com/v1/public/comics/7741","date":"1989-10-20T00:00:00-0400","price":0.0,"thumbnail":"http://i.annihil.us/u/prod/marvel/i/mg/5/f0/4f206d529a4a2/portrait_medium.jpg"},{"id":7740,"title":"Captain America (1968) #359","issueNumber":359.0,"resourceURI":"http://gateway.marvel.com/v1/public/comics/7740","date":"1989-10-10T00:00:00-0400","price":0.0,"thumbnail":"http://i.annihil.us/u/prod/marvel/i/mg/3/c0/4f206b69e0865/portrait_medium.jpg"},{"id":7739,"title":"Captain America (1968) #358","issueNumber":358.0,"resourceURI":"http://gateway.marvel.com/v1/public/comics/7739","date":"1989-09-20T00:00:00-0400","price":0.0,"thumbnail":"http://i.annihil.us/u/prod/marvel/i/mg/9/d0/4f2067943feec/portrait_medium.jpg"},{"id":7738,"title":"Captain America (1968) #357","issueNumber":357.0,"resourceURI":"http://gateway.marvel.com/v1/public/comics/7738","date":"1989-09-10T00:00:00-0400","price":0.0,"thumbnail":"http://i.annihil.us/u/prod/marvel/i/mg/6/b0/5176ddf607d17/portrait_medium.jpg"},{"id":7737,"title":"Captain America (1968) #356","issueNumber":356.0,"resourceURI":"http://gateway.marvel.com/v1/public/comics/7737","date":"1989-08-10T00:00:00-0400","price":0.0,"thumbnail":"http://i.annihil.us/u/prod/marvel/i/mg/d/a0/51f1877251185/portrait_medium.jpg"},{"id":7736,"title":"Captain America (1968) #355","issueNumber":355.0,"resourceURI":"http://gateway.marvel.com/v1/public/comics/7736","date":"1989-07-10T00:00:00-0400","price":0.0,"thumbnail":"http://i.annihil.us/u/prod/marvel/i/mg/3/00/5176b3bd73700/portrait_medium.jpg"},{"id":7735,"title":"Captain America (1968) #354","issueNumber":354.0,"resourceURI":"http://gateway.marvel.com/v1/public/comics/7735","date":"1989-06-10T00:00:00-0400","price":0.0,"thumbnail":"http://i.annihil.us/u/prod/marvel/i/mg/9/80/5294faed1273f/portrait_medium.jpg"},{"id":7734,"title":"Captain America (1968) #353","issueNumber":353.0,"resourceURI":"http://gateway.marvel.com/v1/public/comics/7734","date":"1989-05-10T00:00:00-0400","price":0.0,"thumbnail":"http://i.annihil.us/u/prod/marvel/i/mg/9/70/56e6de90ec402/portrait_medium.jpg"},{"id":7733,"title":"Captain America (1968) #352","issueNumber":352.0,"resourceURI":"http://gateway.marvel.com/v1/public/comics/7733","date":"1989-04-10T00:00:00-0400","price":0.0,"thumbnail":"http://i.annihil.us/u/prod/marvel/i/mg/6/50/52ab9b349d641/portrait_medium.jpg"},{"id":7732,"title":"Captain America (1968) #351","issueNumber":351.0,"resourceURI":"http://gateway.marvel.com/v1/public/comics/7732","date":"1989-03-10T00:00:00-0500","price":0.0,"thumbnail":"http://i.annihil.us/u/prod/marvel/i/mg/4/00/52950f849ab84/portrait_medium.jpg"},{"id":7731,"title":"Captain America (1968) #350","issueNumber":350.0,"resourceURI":"http://gateway.marvel.com/v1/public/comics/7731","date":"1989-02-10T00:00:00-0500","price":0.0,"thumbnail":"http://i.annihil.us/u/prod/marvel/i/mg/a/10/56e6dd96415de/portrait_medium.jpg"},{"id":7730,"title":"Captain America (1968) #349","issueNumber":349.0,"resourceURI":"http://gateway.marvel.com/v1/public/comics/7730","date":"1989-01-10T00:00:00-0500","price":0.0,"thumbnail":"http://i.annihil.us/u/prod/marvel/i/mg/c/70/56e6dd39bca42/portrait_medium.jpg"},{"id":7729,"title":"Captain America (1968) #348","issueNumber":348.0,"resourceURI":"http://gateway.marvel.com/v1/public/comics/7729","date":"1988-12-10T00:00:00-0500","price":0.0,"thumbnail":"http://i.annihil.us/u/prod/marvel/i/mg/3/70/56e6dc7181611/portrait_medium.jpg"},{"id":7728,"title":"Captain America (1968) #347","issueNumber":347.0,"resourceURI":"http://gateway.marvel.com/v1/public/comics/7728","date":"1988-11-10T00:00:00-0500","price":0.0,"thumbnail":"http://i.annihil.us/u/prod/marvel/i/mg/a/90/56e6dbe5868c9/portrait_medium.jpg"},{"id":7727,"title":"Captain America (1968) #346","issueNumber":346.0,"resourceURI":"http://gateway.marvel.com/v1/public/comics/7727","date":"1988-10-10T00:00:00-0400","price":0.0,"thumbnail":"http://i.annihil.us/u/prod/marvel/i/mg/c/b0/56e6dabfc1883/portrait_medium.jpg"},{"id":7726,"title":"Captain America (1968) #345","issueNumber":345.0,"resourceURI":"http://gateway.marvel.com/v1/public/comics/7726","date":"1988-09-10T00:00:00-0400","price":0.0,"thumbnail":"http://i.annihil.us/u/prod/marvel/i/mg/9/60/56e6da3db5183/portrait_medium.jpg"},{"id":7725,"title":"Captain America (1968) #344","issueNumber":344.0,"resourceURI":"http://gateway.marvel.com/v1/public/comics/7725","date":"1988-08-10T00:00:00-0400","price":0.0,"thumbnail":"http://i.annihil.us/u/prod/marvel/i/mg/6/a0/56e6d8c040c58/portrait_medium.jpg"},{"id":7724,"title":"Captain America (1968) #343","issueNumber":343.0,"resourceURI":"http://gateway.marvel.com/v1/public/comics/7724","date":"1988-07-10T00:00:00-0400","price":0.0,"thumbnail":"http://i.annihil.us/u/prod/marvel/i/mg/a/20/56e6d85176dce/portrait_medium.jpg"},{"id":7723,"title":"Captain America (1968) #342","issueNumber":342.0,"resourceURI":"http://gateway.marvel.com/v1/public/comics/7723","date":"1988-06-10T00:00:00-0400","price":0.0,"thumbnail":"http://i.annihil.us/u/prod/marvel/i/mg/c/30/56e6d7d02dcb2/portrait_medium.jpg"},{"id":7722,"title":"Captain America (1968) #341","issueNumber":341.0,"resourceURI":"http://gateway.marvel.com/v1/public/comics/7722","date":"1988-05-10T00:00:00-0400","price":0.0,"thumbnail":"http://i.annihil.us/u/prod/marvel/i/mg/9/c0/52c5a49c96cd5/portrait_medium.jpg"},{"id":7721,"title":"Captain America (1968) #340","issueNumber":340.0,"resourceURI":"http://gateway.marvel.com/v1/public/comics/7721","date":"1988-04-10T00:00:00-0400","price":0.0,"thumbnail":"http://i.annihil.us/u/prod/marvel/i/mg/6/70/59a6d642d91b1/portrait_medium.jpg"},{"id":7720,"title":"Captain America (1968) #339","issueNumber":339.0,"resourceURI":"http://gateway.marvel.com/v1/public/comics/7720","date":"1988-03-10T00:00:00-0500","price":0.0,"thumbnail":"http://i.annihil.us/u/prod/marvel/i/mg/d/70/526176f761007/portrait_medium.jpg"},{"id":7719,"title":"Captain America (1968) #338","issueNumber":338.0,"resourceURI":"http://gateway.marvel.com/v1/public/comics/7719","date":"1988-02-10T00:00:00-0500","price":0.0,"thumbnail":"http://i.annihil.us/u/prod/marvel/i/mg/9/03/56e6d70018635/portrait_medium.jpg"},{"id":7718,"title":"Captain America (1968) #337","issueNumber":337.0,"resourceURI":"http://gateway.marvel.com/v1/public/comics/7718","date":"1988-01-10T00:00:00-0500","price":0.0,"thumbnail":"http://i.annihil.us/u/prod/marvel/i/mg/4/60/56e6d69743a76/portrait_medium.jpg"},{"id":7717,"title":"Captain America (1968) #336","issueNumber":336.0,"resourceURI":"http://gateway.marvel.com/v1/public/comics/7717","date":"1987-12-10T00:00:00-0500","price":0.0,"thumbnail":"http://i.annihil.us/u/prod/marvel/i/mg/9/80/56e6d5fc1820d/portrait_medium.jpg"},{"id":7716,"title":"Captain America (1968) #335","issueNumber":335.0,"resourceURI":"http://gateway.marvel.com/v1/public/comics/7716","date":"1987-11-10T00:00:00-0500","price":0.0,"thumbnail":"http://i.annihil.us/u/prod/marvel/i/mg/3/a0/50ad4790f2388/portrait_medium.jpg"},{"id":7715,"title":"Captain America (1968) #334","issueNumber":334.0,"resourceURI":"http://gateway.marvel.com/v1/public/comics/7715","date":"1987-10-10T00:00:00-0400","price":0.0,"thumbnail":"http://i.annihil.us/u/prod/marvel/i/mg/b/90/50b52dc1f3c5a/portrait_medium.jpg"},{"id":7714,"title":"Captain America (1968) #333","issueNumber":333.0,"resourceURI":"http://gateway.marvel.com/v1/public/comics/7714","date":"1987-09-10T00:00:00-0400","price":0.0,"thumbnail":"http://i.annihil.us/u/prod/marvel/i/mg/8/40/50b40d6bc124b/portrait_medium.jpg"},{"id":7713,"title":"Captain America (1968) #332","issueNumber":332.0,"resourceURI":"http://gateway.marvel.com/v1/public/comics/7713","date":"1987-08-10T00:00:00-0400","price":0.0,"thumbnail":"http://i.annihil.us/u/prod/marvel/i/mg/c/20/59a5b0e5c9b0c/portrait_medium.jpg"},{"id":7712,"title":"Captain America (1968) #331","issueNumber":331.0,"resourceURI":"http://gateway.marvel.com/v1/public/comics/7712","date":"1987-07-10T00:00:00-0400","price":0.0,"thumbnail":"http://i.annihil.us/u/prod/marvel/i/mg/b/20/5266971970436/portrait_medium.jpg"},{"id":7711,"title":"Captain America (1968) #330","issueNumber":330.0,"resourceURI":"http://gateway.marvel.com/v1/public/comics/7711","date":"1987-06-10T00:00:00-0400","price":0.0,"thumbnail":"http://i.annihil.us/u/prod/marvel/i/mg/e/60/526697516f385/portrait_medium.jpg"},{"id":7710,"title":"Captain America (1968) #329","issueNumber":329.0,"resourceURI":"http://gateway.marvel.com/v1/public/comics/7710","date":"1987-05-10T00:00:00-0400","price":0.0,"thumbnail":"http://i.annihil.us/u/prod/marvel/i/mg/c/b0/52ab9b69c8ba8/portrait_medium.jpg"},{"id":7709,"title":"Captain America (1968) #328","issueNumber":328.0,"resourceURI":"http://gateway.marvel.com/v1/public/comics/7709","date":"1987-04-10T00:00:00-0400","price":0.0,"thumbnail":"http://i.annihil.us/u/prod/marvel/i/mg/9/e0/59a58a684a6af/portrait_medium.jpg"},{"id":7708,"title":"Captain America (1968) #327","issueNumber":327.0,"resourceURI":"http://gateway.marvel.com/v1/public/comics/7708","date":"1987-03-10T00:00:00-0500","price":0.0,"thumbnail":"http://i.annihil.us/u/prod/marvel/i/mg/6/80/5294fb6166b3c/portrait_medium.jpg"},{"id":7707,"title":"Captain America (1968) #326","issueNumber":326.0,"resourceURI":"http://gateway.marvel.com/v1/public/comics/7707","date":"1987-02-10T00:00:00-0500","price":0.0,"thumbnail":"http://i.annihil.us/u/prod/marvel/i/mg/8/03/59a5754233b18/portrait_medium.jpg"},{"id":7706,"title":"Captain America (1968) #325","issueNumber":325.0,"resourceURI":"http://gateway.marvel.com/v1/public/comics/7706","date":"1987-01-10T00:00:00-0500","price":0.0,"thumbnail":"http://i.annihil.us/u/prod/marvel/i/mg/9/a0/5204024657312/portrait_medium.jpg"},{"id":7705,"title":"Captain America (1968) #324","issueNumber":324.0,"resourceURI":"http://gateway.marvel.com/v1/public/comics/7705","date":"1986-12-10T00:00:00-0500","price":0.0,"thumbnail":"http://i.annihil.us/u/prod/marvel/i/mg/b/d0/5203fc6ecce12/portrait_medium.jpg"},{"id":7704,"title":"Captain America (1968) #323","issueNumber":323.0,"resourceURI":"http://gateway.marvel.com/v1/public/comics/7704","date":"1986-11-10T00:00:00-0500","price":0.0,"thumbnail":"http://i.annihil.us/u/prod/marvel/i/mg/9/03/5203f439e2746/portrait_medium.jpg"},{"id":7703,"title":"Captain America (1968) #322","issueNumber":322.0,"resourceURI":"http://gateway.marvel.com/v1/public/comics/7703","date":"1986-10-10T00:00:00-0400","price":0.0,"thumbnail":"http://i.annihil.us/u/prod/marvel/i/mg/c/20/51fad119cfc27/portrait_medium.jpg"},{"id":7702,"title":"Captain America (1968) #321","issueNumber":321.0,"resourceURI":"http://gateway.marvel.com/v1/public/comics/7702","date":"1986-09-10T00:00:00-0400","price":0.0,"thumbnail":"http://i.annihil.us/u/prod/marvel/i/mg/4/90/51fad14bbecae/portrait_medium.jpg"},{"id":7701,"title":"Captain America (1968) #320","issueNumber":320.0,"resourceURI":"http://gateway.marvel.com/v1/public/comics/7701","date":"1986-08-10T00:00:00-0400","price":0.0,"thumbnail":"http://i.annihil.us/u/prod/marvel/i/mg/c/d0/56e6d3d909cae/portrait_medium.jpg"},{"id":7700,"title":"Captain America (1968) #319","issueNumber":319.0,"resourceURI":"http://gateway.marvel.com/v1/public/comics/7700","date":"1986-07-10T00:00:00-0400","price":0.0,"thumbnail":"http://i.annihil.us/u/prod/marvel/i/mg/f/a0/56e6d2cee63fa/portrait_medium.jpg"},{"id":7699,"title":"Captain America (1968) #318","issueNumber":318.0,"resourceURI":"http://gateway.marvel.com/v1/public/comics/7699","date":"1986-06-10T00:00:00-0400","price":0.0,"thumbnail":"http://i.annihil.us/u/prod/marvel/i/mg/7/70/56e6d1e96c974/portrait_medium.jpg"},{"id":7698,"title":"Captain America (1968) #317","issueNumber":317.0,"resourceURI":"http://gateway.marvel.com/v1/public/comics/7698","date":"1986-05-10T00:00:00-0400","price":0.0,"thumbnail":"http://i.annihil.us/u/prod/marvel/i/mg/e/f0/51fad17ccb7c3/portrait_medium.jpg"},{"id":7697,"title":"Captain America (1968) #316","issueNumber":316.0,"resourceURI":"http://gateway.marvel.com/v1/public/comics/7697","date":"1986-04-10T00:00:00-0500","price":0.0,"thumbnail":"http://i.annihil.us/u/prod/marvel/i/mg/f/10/51fad1ad79a5c/portrait_medium.jpg"},{"id":7696,"title":"Captain America (1968) #315","issueNumber":315.0,"resourceURI":"http://gateway.marvel.com/v1/public/comics/7696","date":"1986-03-10T00:00:00-0500","price":0.0,"thumbnail":"http://i.annihil.us/u/prod/marvel/i/mg/7/10/59a428dd08f85/portrait_medium.jpg"},{"id":7695,"title":"Captain America (1968) #314","issueNumber":314.0,"resourceURI":"http://gateway.marvel.com/v1/public/comics/7695","date":"1986-02-10T00:00:00-0500","price":0.0,"thumbnail":"http://i.annihil.us/u/prod/marvel/i/mg/9/30/4bb6ee47185a0/portrait_medium.jpg"},{"id":7694,"title":"Captain America (1968) #313","issueNumber":313.0,"resourceURI":"http://gateway.marvel.com/v1/public/comics/7694","date":"1986-01-10T00:00:00-0500","price":0.0,"thumbnail":"http://i.annihil.us/u/prod/marvel/i/mg/2/70/5217d1003be53/portrait_medium.jpg"},{"id":7693,"title":"Captain America (1968) #312","issueNumber":312.0,"resourceURI":"http://gateway.marvel.com/v1/public/comics/7693","date":"1985-12-10T00:00:00-0500","price":0.0,"thumbnail":"http://i.annihil.us/u/prod/marvel/i/mg/b/a0/51fad1e0dd307/portrait_medium.jpg"},{"id":7692,"title":"Captain America (1968) #311","issueNumber":311.0,"resourceURI":"http://gateway.marvel.com/v1/public/comics/7692","date":"1985-11-10T00:00:00-0500","price":0.0,"thumbnail":"http://i.annihil.us/u/prod/marvel/i/mg/a/a0/59a07d9e8f77e/portrait_medium.jpg"},{"id":7691,"title":"Captain America (1968) #310","issueNumber":310.0,"resourceURI":"http://gateway.marvel.com/v1/public/comics/7691","date":"1985-10-10T00:00:00-0400","price":0.0,"thumbnail":"http://i.annihil.us/u/prod/marvel/i/mg/7/60/52669789acb5f/portrait_medium.jpg"},{"id":7690,"title":"Captain America (1968) #309","issueNumber":309.0,"resourceURI":"http://gateway.marvel.com/v1/public/comics/7690","date":"1985-09-10T00:00:00-0400","price":0.0,"thumbnail":"http://i.annihil.us/u/prod/marvel/i/mg/4/30/52668e6d7d238/portrait_medium.jpg"},{"id":7689,"title":"Captain America (1968) #308","issueNumber":308.0,"resourceURI":"http://gateway.marvel.com/v1/public/comics/7689","date":"1985-08-10T00:00:00-0400","price":0.0,"thumbnail":"http://i.annihil.us/u/prod/marvel/i/mg/b/f0/5155e8c1db3ca/portrait_medium.jpg"},{"id":7688,"title":"Captain America (1968) #307","issueNumber":307.0,"resourceURI":"http://gateway.marvel.com/v1/public/comics/7688","date":"1985-07-10T00:00:00-0400","price":0.0,"thumbnail":"http://i.annihil.us/u/prod/marvel/i/mg/c/f0/52668eaaa8f7f/portrait_medium.jpg"},{"id":7687,"title":"Captain America (1968) #306","issueNumber":306.0,"resourceURI":"http://gateway.marvel.com/v1/public/comics/7687","date":"1985-06-10T00:00:00-0400","price":0.0,"thumbnail":"http://i.annihil.us/u/prod/marvel/i/mg/3/20/50ad69111b649/portrait_medium.jpg"},{"id":7686,"title":"Captain America (1968) #305","issueNumber":305.0,"resourceURI":"http://gateway.marvel.com/v1/public/comics/7686","date":"1985-05-10T00:00:00-0400","price":0.0,"thumbnail":"http://i.annihil.us/u/prod/marvel/i/mg/c/03/50ad698538028/portrait_medium.jpg"},{"id":7685,"title":"Captain America (1968) #304","issueNumber":304.0,"resourceURI":"http://gateway.marvel.com/v1/public/comics/7685","date":"1985-04-10T00:00:00-0500","price":0.0,"thumbnail":"http://i.annihil.us/u/prod/marvel/i/mg/9/40/51f12ad7e764b/portrait_medium.jpg"},{"id":7684,"title":"Captain America (1968) #303","issueNumber":303.0,"resourceURI":"http://gateway.marvel.com/v1/public/comics/7684","date":"1985-03-10T00:00:00-0500","price":0.0,"thumbnail":"http://i.annihil.us/u/prod/marvel/i/mg/3/00/51fad21467523/portrait_medium.jpg"},{"id":7683,"title":"Captain America (1968) #302","issueNumber":302.0,"resourceURI":"http://gateway.marvel.com/v1/public/comics/7683","date":"1985-02-10T00:00:00-0500","price":0.0,"thumbnail":"http://i.annihil.us/u/prod/marvel/i/mg/3/30/51f04408c472f/portrait_medium.jpg"},{"id":7682,"title":"Captain America (1968) #301","issueNumber":301.0,"resourceURI":"http://gateway.marvel.com/v1/public/comics/7682","date":"1985-01-10T00:00:00-0500","price":0.0,"thumbnail":"http://i.annihil.us/u/prod/marvel/i/mg/3/70/51f187b3c2484/portrait_medium.jpg"},{"id":7681,"title":"Captain America (1968) #300","issueNumber":300.0,"resourceURI":"http://gateway.marvel.com/v1/public/comics/7681","date":"1984-12-10T00:00:00-0500","price":0.0,"thumbnail":"http://i.annihil.us/u/prod/marvel/i/mg/6/10/56e6cf023450c/portrait_medium.jpg"},{"id":7680,"title":"Captain America (1968) #299","issueNumber":299.0,"resourceURI":"http://gateway.marvel.com/v1/public/comics/7680","date":"1984-11-10T00:00:00-0500","price":0.0,"thumbnail":"http://i.annihil.us/u/prod/marvel/i/mg/d/20/5155c42422277/portrait_medium.jpg"},{"id":7679,"title":"Captain America (1968) #298","issueNumber":298.0,"resourceURI":"http://gateway.marvel.com/v1/public/comics/7679","date":"1984-10-10T00:00:00-0400","price":0.0,"thumbnail":"http://i.annihil.us/u/prod/marvel/i/mg/3/b0/5155be4645a69/portrait_medium.jpg"},{"id":7678,"title":"Captain America (1968) #297","issueNumber":297.0,"resourceURI":"http://gateway.marvel.com/v1/public/comics/7678","date":"1984-09-10T00:00:00-0400","price":0.0,"thumbnail":"http://i.annihil.us/u/prod/marvel/i/mg/b/03/5154b3167963f/portrait_medium.jpg"},{"id":7677,"title":"Captain America (1968) #296","issueNumber":296.0,"resourceURI":"http://gateway.marvel.com/v1/public/comics/7677","date":"1984-08-10T00:00:00-0400","price":0.0,"thumbnail":"http://i.annihil.us/u/prod/marvel/i/mg/2/c0/5154a50b15b48/portrait_medium.jpg"},{"id":7676,"title":"Captain America (1968) #295","issueNumber":295.0,"resourceURI":"http://gateway.marvel.com/v1/public/comics/7676","date":"1984-07-10T00:00:00-0400","price":0.0,"thumbnail":"http://i.annihil.us/u/prod/marvel/i/mg/e/20/515496f830864/portrait_medium.jpg"},{"id":7675,"title":"Captain America (1968) #294","issueNumber":294.0,"resourceURI":"http://gateway.marvel.com/v1/public/comics/7675","date":"1984-06-10T00:00:00-0400","price":0.0,"thumbnail":"http://i.annihil.us/u/prod/marvel/i/mg/1/10/51548f08b0979/portrait_medium.jpg"},{"id":7674,"title":"Captain America (1968) #293","issueNumber":293.0,"resourceURI":"http://gateway.marvel.com/v1/public/comics/7674","date":"1984-05-10T00:00:00-0400","price":0.0,"thumbnail":"http://i.annihil.us/u/prod/marvel/i/mg/5/d0/515480b5a7b1c/portrait_medium.jpg"},{"id":7673,"title":"Captain America (1968) #292","issueNumber":292.0,"resourceURI":"http://gateway.marvel.com/v1/public/comics/7673","date":"1984-04-10T00:00:00-0500","price":0.0,"thumbnail":"http://i.annihil.us/u/prod/marvel/i/mg/6/50/51547ad76d70a/portrait_medium.jpg"},{"id":7672,"title":"Captain America (1968) #291","issueNumber":291.0,"resourceURI":"http://gateway.marvel.com/v1/public/comics/7672","date":"1984-03-10T00:00:00-0500","price":0.6,"thumbnail":"http://i.annihil.us/u/prod/marvel/i/mg/4/20/599ef34a42881/portrait_medium.jpg"},{"id":7671,"title":"Captain America (1968) #290","issueNumber":290.0,"resourceURI":"http://gateway.marvel.com/v1/public/comics/7671","date":"1984-02-10T00:00:00-0500","price":0.0,"thumbnail":"http://i.annihil.us/u/prod/marvel/i/mg/8/e0/59a0524a0dcd7/portrait_medium.jpg"},{"id":7670,"title":"Captain America (1968) #289","issueNumber":289.0,"resourceURI":"http://gateway.marvel.com/v1/public/comics/7670","date":"1984-01-10T00:00:00-0500","price":0.0,"thumbnail":"http://i.annihil.us/u/prod/marvel/i/mg/6/f0/51ed92f8544d5/portrait_medium.jpg"},{"id":7669,"title":"Captain America (1968) #288","issueNumber":288.0,"resourceURI":"http://gateway.marvel.com/v1/public/comics/7669","date":"1983-12-10T00:00:00-0500","price":0.0,"thumbnail":"http://i.annihil.us/u/prod/marvel/i/mg/e/d0/50ad70fed0ad7/portrait_medium.jpg"},{"id":7668,"title":"Captain America (1968) #287","issueNumber":287.0,"resourceURI":"http://gateway.marvel.com/v1/public/comics/7668","date":"1983-11-10T00:00:00-0500","price":0.0,"thumbnail":"http://i.annihil.us/u/prod/marvel/i/mg/6/00/59a051220eb9f/portrait_medium.jpg"},{"id":7667,"title":"Captain America (1968) #286","issueNumber":286.0,"resourceURI":"http://gateway.marvel.com/v1/public/comics/7667","date":"1983-10-10T00:00:00-0400","price":0.0,"thumbnail":"http://i.annihil.us/u/prod/marvel/i/mg/9/50/50ad71950aef8/portrait_medium.jpg"},{"id":7666,"title":"Captain America (1968) #285","issueNumber":285.0,"resourceURI":"http://gateway.marvel.com/v1/public/comics/7666","date":"1983-09-10T00:00:00-0400","price":0.0,"thumbnail":"http://i.annihil.us/u/prod/marvel/i/mg/a/70/5294fbff92e59/portrait_medium.jpg"},{"id":7665,"title":"Captain America (1968) #284","issueNumber":284.0,"resourceURI":"http://gateway.marvel.com/v1/public/comics/7665","date":"1983-08-10T00:00:00-0400","price":0.0,"thumbnail":"http://i.annihil.us/u/prod/marvel/i/mg/4/70/52616fd9d3897/portrait_medium.jpg"},{"id":7664,"title":"Captain America (1968) #283","issueNumber":283.0,"resourceURI":"http://gateway.marvel.com/v1/public/comics/7664","date":"1983-07-10T00:00:00-0400","price":0.0,"thumbnail":"http://i.annihil.us/u/prod/marvel/i/mg/6/50/59a04d94ba193/portrait_medium.jpg"},{"id":7663,"title":"Captain America (1968) #282","issueNumber":282.0,"resourceURI":"http://gateway.marvel.com/v1/public/comics/7663","date":"1983-06-10T00:00:00-0400","price":0.0,"thumbnail":"http://i.annihil.us/u/prod/marvel/i/mg/9/50/51f035f562dde/portrait_medium.jpg"},{"id":7662,"title":"Captain America (1968) #281","issueNumber":281.0,"resourceURI":"http://gateway.marvel.com/v1/public/comics/7662","date":"1983-05-10T00:00:00-0400","price":0.0,"thumbnail":"http://i.annihil.us/u/prod/marvel/i/mg/3/40/59a04cb738360/portrait_medium.jpg"},{"id":7661,"title":"Captain America (1968) #280","issueNumber":280.0,"resourceURI":"http://gateway.marvel.com/v1/public/comics/7661","date":"1983-04-10T00:00:00-0500","price":0.0,"thumbnail":"http://i.annihil.us/u/prod/marvel/i/mg/1/03/59a04a2853253/portrait_medium.jpg"},{"id":7660,"title":"Captain America (1968) #279","issueNumber":279.0,"resourceURI":"http://gateway.marvel.com/v1/public/comics/7660","date":"1983-03-10T00:00:00-0500","price":0.0,"thumbnail":"http://i.annihil.us/u/prod/marvel/i/mg/b/e0/51ed68c3ba33a/portrait_medium.jpg"},{"id":7659,"title":"Captain America (1968) #278","issueNumber":278.0,"resourceURI":"http://gateway.marvel.com/v1/public/comics/7659","date":"1983-02-10T00:00:00-0500","price":0.0,"thumbnail":"http://i.annihil.us/u/prod/marvel/i/mg/5/d0/51f00c2e3617e/portrait_medium.jpg"},{"id":7658,"title":"Captain America (1968) #277","issueNumber":277.0,"resourceURI":"http://gateway.marvel.com/v1/public/comics/7658","date":"1983-01-10T00:00:00-0500","price":0.0,"thumbnail":"http://i.annihil.us/u/prod/marvel/i/mg/6/00/51f00c65b5e90/portrait_medium.jpg"},{"id":7657,"title":"Captain America (1968) #276","issueNumber":276.0,"resourceURI":"http://gateway.marvel.com/v1/public/comics/7657","date":"1982-12-10T00:00:00-0500","price":0.0,"thumbnail":"http://i.annihil.us/u/prod/marvel/i/mg/e/d0/51ed5aad33b4f/portrait_medium.jpg"},{"id":7656,"title":"Captain America (1968) #275","issueNumber":275.0,"resourceURI":"http://gateway.marvel.com/v1/public/comics/7656","date":"1982-11-10T00:00:00-0500","price":0.0,"thumbnail":"http://i.annihil.us/u/prod/marvel/i/mg/f/90/51ed5ae57ab9f/portrait_medium.jpg"},{"id":7655,"title":"Captain America (1968) #274","issueNumber":274.0,"resourceURI":"http://gateway.marvel.com/v1/public/comics/7655","date":"1982-10-10T00:00:00-0400","price":0.0,"thumbnail":"http://i.annihil.us/u/prod/marvel/i/mg/c/50/56e6cd229b2db/portrait_medium.jpg"},{"id":7654,"title":"Captain America (1968) #273","issueNumber":273.0,"resourceURI":"http://gateway.marvel.com/v1/public/comics/7654","date":"1982-09-10T00:00:00-0400","price":0.0,"thumbnail":"http://i.annihil.us/u/prod/marvel/i/mg/3/30/51f94cb713630/portrait_medium.jpg"},{"id":7653,"title":"Captain America (1968) #272","issueNumber":272.0,"resourceURI":"http://gateway.marvel.com/v1/public/comics/7653","date":"1982-08-10T00:00:00-0400","price":0.0,"thumbnail":"http://i.annihil.us/u/prod/marvel/i/mg/6/f0/51f94ce847d15/portrait_medium.jpg"},{"id":7652,"title":"Captain America (1968) #271","issueNumber":271.0,"resourceURI":"http://gateway.marvel.com/v1/public/comics/7652","date":"1982-07-10T00:00:00-0400","price":0.0,"thumbnail":"http://i.annihil.us/u/prod/marvel/i/mg/3/30/51f94d19011a8/portrait_medium.jpg"},{"id":7651,"title":"Captain America (1968) #270","issueNumber":270.0,"resourceURI":"http://gateway.marvel.com/v1/public/comics/7651","date":"1982-06-10T00:00:00-0400","price":0.6,"thumbnail":"http://i.annihil.us/u/prod/marvel/i/mg/3/90/51f94d516253e/portrait_medium.jpg"},{"id":7650,"title":"Captain America (1968) #269","issueNumber":269.0,"resourceURI":"http://gateway.marvel.com/v1/public/comics/7650","date":"1982-05-10T00:00:00-0400","price":0.0,"thumbnail":"http://i.annihil.us/u/prod/marvel/i/mg/4/20/51f94d811968c/portrait_medium.jpg"},{"id":7649,"title":"Captain America (1968) #268","issueNumber":268.0,"resourceURI":"http://gateway.marvel.com/v1/public/comics/7649","date":"1982-04-10T00:00:00-0500","price":0.0,"thumbnail":"http://i.annihil.us/u/prod/marvel/i/mg/d/60/56e6cb7ee89b6/portrait_medium.jpg"},{"id":7648,"title":"Captain America (1968) #267","issueNumber":267.0,"resourceURI":"http://gateway.marvel.com/v1/public/comics/7648","date":"1982-03-10T00:00:00-0500","price":0.0,"thumbnail":"http://i.annihil.us/u/prod/marvel/i/mg/9/70/51f947bd0d6c3/portrait_medium.jpg"},{"id":7647,"title":"Captain America (1968) #266","issueNumber":266.0,"resourceURI":"http://gateway.marvel.com/v1/public/comics/7647","date":"1982-02-10T00:00:00-0500","price":0.0,"thumbnail":"http://i.annihil.us/u/prod/marvel/i/mg/3/c0/5382c665275be/portrait_medium.jpg"},{"id":7646,"title":"Captain America (1968) #265","issueNumber":265.0,"resourceURI":"http://gateway.marvel.com/v1/public/comics/7646","date":"1982-01-10T00:00:00-0500","price":0.0,"thumbnail":"http://i.annihil.us/u/prod/marvel/i/mg/6/f0/5382c698b57ac/portrait_medium.jpg"},{"id":7645,"title":"Captain America (1968) #264","issueNumber":264.0,"resourceURI":"http://gateway.marvel.com/v1/public/comics/7645","date":"1981-12-10T00:00:00-0500","price":0.0,"thumbnail":"http://i.annihil.us/u/prod/marvel/i/mg/8/d0/5382c6cd0a25b/portrait_medium.jpg"},{"id":7644,"title":"Captain America (1968) #263","issueNumber":263.0,"resourceURI":"http://gateway.marvel.com/v1/public/comics/7644","date":"1981-11-10T00:00:00-0500","price":0.0,"thumbnail":"http://i.annihil.us/u/prod/marvel/i/mg/d/30/56e6c8dfbf663/portrait_medium.jpg"},{"id":7643,"title":"Captain America (1968) #262","issueNumber":262.0,"resourceURI":"http://gateway.marvel.com/v1/public/comics/7643","date":"1981-10-10T00:00:00-0400","price":0.0,"thumbnail":"http://i.annihil.us/u/prod/marvel/i/mg/c/a0/56e6c6f0e5df0/portrait_medium.jpg"},{"id":7642,"title":"Captain America (1968) #261","issueNumber":261.0,"resourceURI":"http://gateway.marvel.com/v1/public/comics/7642","date":"1981-09-10T00:00:00-0400","price":0.0,"thumbnail":"http://i.annihil.us/u/prod/marvel/i/mg/9/20/56e6c3ac20b85/portrait_medium.jpg"},{"id":7641,"title":"Captain America (1968) #260","issueNumber":260.0,"resourceURI":"http://gateway.marvel.com/v1/public/comics/7641","date":"1981-08-10T00:00:00-0400","price":0.0,"thumbnail":"http://i.annihil.us/u/prod/marvel/i/mg/2/03/5382c703935a0/portrait_medium.jpg"},{"id":7640,"title":"Captain America (1968) #259","issueNumber":259.0,"resourceURI":"http://gateway.marvel.com/v1/public/comics/7640","date":"1981-07-10T00:00:00-0400","price":0.0,"thumbnail":"http://i.annihil.us/u/prod/marvel/i/mg/4/10/5382c7373e4e9/portrait_medium.jpg"},{"id":7639,"title":"Captain America (1968) #258","issueNumber":258.0,"resourceURI":"http://gateway.marvel.com/v1/public/comics/7639","date":"1981-06-10T00:00:00-0400","price":0.0,"thumbnail":"http://i.annihil.us/u/prod/marvel/i/mg/6/60/5382c76b35db3/portrait_medium.jpg"},{"id":7638,"title":"Captain America (1968) #257","issueNumber":257.0,"resourceURI":"http://gateway.marvel.com/v1/public/comics/7638","date":"1981-05-10T00:00:00-0400","price":0.0,"thumbnail":"http://i.annihil.us/u/prod/marvel/i/mg/4/80/5382c79f4676e/portrait_medium.jpg"},{"id":7637,"title":"Captain America (1968) #256","issueNumber":256.0,"resourceURI":"http://gateway.marvel.com/v1/public/comics/7637","date":"1981-04-10T00:00:00-0500","price":0.0,"thumbnail":"http://i.annihil.us/u/prod/marvel/i/mg/5/c0/5382c7d1bb501/portrait_medium.jpg"},{"id":7636,"title":"Captain America (1968) #255","issueNumber":255.0,"resourceURI":"http://gateway.marvel.com/v1/public/comics/7636","date":"1981-03-10T00:00:00-0500","price":0.0,"thumbnail":"http://i.annihil.us/u/prod/marvel/i/mg/c/60/4bb6ee4c6f109/portrait_medium.jpg"},{"id":7635,"title":"Captain America (1968) #254","issueNumber":254.0,"resourceURI":"http://gateway.marvel.com/v1/public/comics/7635","date":"1981-02-10T00:00:00-0500","price":0.0,"thumbnail":"http://i.annihil.us/u/prod/marvel/i/mg/c/00/4bb6ee51bc804/portrait_medium.jpg"},{"id":7634,"title":"Captain America (1968) #253","issueNumber":253.0,"resourceURI":"http://gateway.marvel.com/v1/public/comics/7634","date":"1981-01-10T00:00:00-0500","price":0.0,"thumbnail":"http://i.annihil.us/u/prod/marvel/i/mg/9/90/4bb6ee56e2626/portrait_medium.jpg"},{"id":7633,"title":"Captain America (1968) #252","issueNumber":252.0,"resourceURI":"http://gateway.marvel.com/v1/public/comics/7633","date":"1980-12-10T00:00:00-0500","price":0.0,"thumbnail":"http://i.annihil.us/u/prod/marvel/i/mg/f/20/4bb6ee5c3c2a8/portrait_medium.jpg"},{"id":7632,"title":"Captain America (1968) #251","issueNumber":251.0,"resourceURI":"http://gateway.marvel.com/v1/public/comics/7632","date":"1980-11-10T00:00:00-0500","price":0.0,"thumbnail":"http://i.annihil.us/u/prod/marvel/i/mg/9/90/4bb6ee615b369/portrait_medium.jpg"},{"id":7631,"title":"Captain America (1968) #250","issueNumber":250.0,"resourceURI":"http://gateway.marvel.com/v1/public/comics/7631","date":"1980-10-10T00:00:00-0400","price":0.0,"thumbnail":"http://i.annihil.us/u/prod/marvel/i/mg/c/20/4bb6ee71265ca/portrait_medium.jpg"},{"id":7630,"title":"Captain America (1968) #249","issueNumber":249.0,"resourceURI":"http://gateway.marvel.com/v1/public/comics/7630","date":"1980-09-10T00:00:00-0400","price":0.0,"thumbnail":"http://i.annihil.us/u/prod/marvel/i/mg/c/c0/4bb6ee7642f7c/portrait_medium.jpg"},{"id":7629,"title":"Captain America (1968) #248","issueNumber":248.0,"resourceURI":"http://gateway.marvel.com/v1/public/comics/7629","date":"1980-08-10T00:00:00-0400","price":0.0,"thumbnail":"http://i.annihil.us/u/prod/marvel/i/mg/c/b0/4bb6ee7bb8717/portrait_medium.jpg"},{"id":7628,"title":"Captain America (1968) #247","issueNumber":247.0,"resourceURI":"http://gateway.marvel.com/v1/public/comics/7628","date":"1980-07-10T00:00:00-0400","price":0.0,"thumbnail":"http://i.annihil.us/u/prod/marvel/i/mg/9/20/4bb86b9142e0d/portrait_medium.jpg"},{"id":7627,"title":"Captain America (1968) #246","issueNumber":246.0,"resourceURI":"http://gateway.marvel.com/v1/public/comics/7627","date":"1980-06-10T00:00:00-0400","price":0.0,"thumbnail":"http://i.annihil.us/u/prod/marvel/i/mg/4/40/51f947eb29566/portrait_medium.jpg"},{"id":7626,"title":"Captain America (1968) #245","issueNumber":245.0,"resourceURI":"http://gateway.marvel.com/v1/public/comics/7626","date":"1980-05-10T00:00:00-0400","price":0.0,"thumbnail":"http://i.annihil.us/u/prod/marvel/i/mg/3/e0/51f9481b75d72/portrait_medium.jpg"},{"id":7625,"title":"Captain America (1968) #244","issueNumber":244.0,"resourceURI":"http://gateway.marvel.com/v1/public/comics/7625","date":"1980-04-10T00:00:00-0500","price":0.0,"thumbnail":"http://i.annihil.us/u/prod/marvel/i/mg/7/03/51f9484a07405/portrait_medium.jpg"},{"id":7624,"title":"Captain America (1968) #243","issueNumber":243.0,"resourceURI":"http://gateway.marvel.com/v1/public/comics/7624","date":"1980-03-10T00:00:00-0500","price":0.0,"thumbnail":"http://i.annihil.us/u/prod/marvel/i/mg/6/70/51cda8937800e/portrait_medium.jpg"},{"id":7623,"title":"Captain America (1968) #242","issueNumber":242.0,"resourceURI":"http://gateway.marvel.com/v1/public/comics/7623","date":"1980-02-10T00:00:00-0500","price":0.0,"thumbnail":"http://i.annihil.us/u/prod/marvel/i/mg/b/b0/51cda0628bd1e/portrait_medium.jpg"},{"id":7622,"title":"Captain America (1968) #241","issueNumber":241.0,"resourceURI":"http://gateway.marvel.com/v1/public/comics/7622","date":"1980-01-10T00:00:00-0500","price":0.0,"thumbnail":"http://i.annihil.us/u/prod/marvel/i/mg/1/20/526173f28d678/portrait_medium.jpg"},{"id":7621,"title":"Captain America (1968) #240","issueNumber":240.0,"resourceURI":"http://gateway.marvel.com/v1/public/comics/7621","date":"1979-12-10T00:00:00-0500","price":0.0,"thumbnail":"http://i.annihil.us/u/prod/marvel/i/mg/6/90/51cc95328d4c6/portrait_medium.jpg"},{"id":7620,"title":"Captain America (1968) #239","issueNumber":239.0,"resourceURI":"http://gateway.marvel.com/v1/public/comics/7620","date":"1979-11-10T00:00:00-0500","price":0.0,"thumbnail":"http://i.annihil.us/u/prod/marvel/i/mg/9/80/51f9487b5a0af/portrait_medium.jpg"},{"id":7619,"title":"Captain America (1968) #238","issueNumber":238.0,"resourceURI":"http://gateway.marvel.com/v1/public/comics/7619","date":"1979-10-10T00:00:00-0400","price":0.0,"thumbnail":"http://i.annihil.us/u/prod/marvel/i/mg/5/f0/51f948aba0045/portrait_medium.jpg"},{"id":7618,"title":"Captain America (1968) #237","issueNumber":237.0,"resourceURI":"http://gateway.marvel.com/v1/public/comics/7618","date":"1979-09-10T00:00:00-0400","price":0.0,"thumbnail":"http://i.annihil.us/u/prod/marvel/i/mg/9/c0/51f948d9e2a0e/portrait_medium.jpg"},{"id":7617,"title":"Captain America (1968) #236","issueNumber":236.0,"resourceURI":"http://gateway.marvel.com/v1/public/comics/7617","date":"1979-08-10T00:00:00-0400","price":0.0,"thumbnail":"http://i.annihil.us/u/prod/marvel/i/mg/5/b0/51c37112d6b6a/portrait_medium.jpg"},{"id":7616,"title":"Captain America (1968) #235","issueNumber":235.0,"resourceURI":"http://gateway.marvel.com/v1/public/comics/7616","date":"1979-07-10T00:00:00-0400","price":0.35,"thumbnail":"http://i.annihil.us/u/prod/marvel/i/mg/6/d0/51c368da675d7/portrait_medium.jpg"},{"id":7615,"title":"Captain America (1968) #234","issueNumber":234.0,"resourceURI":"http://gateway.marvel.com/v1/public/comics/7615","date":"1979-06-10T00:00:00-0400","price":0.35,"thumbnail":"http://i.annihil.us/u/prod/marvel/i/mg/9/d0/51ed864ed3e37/portrait_medium.jpg"},{"id":7614,"title":"Captain America (1968) #233","issueNumber":233.0,"resourceURI":"http://gateway.marvel.com/v1/public/comics/7614","date":"1979-05-10T00:00:00-0400","price":0.35,"thumbnail":"http://i.annihil.us/u/prod/marvel/i/mg/6/c0/51ed86856ab35/portrait_medium.jpg"},{"id":7613,"title":"Captain America (1968) #232","issueNumber":232.0,"resourceURI":"http://gateway.marvel.com/v1/public/comics/7613","date":"1979-04-10T00:00:00-0500","price":0.35,"thumbnail":"http://i.annihil.us/u/prod/marvel/i/mg/b/e0/51ed86c7aaa21/portrait_medium.jpg"},{"id":7612,"title":"Captain America (1968) #231","issueNumber":231.0,"resourceURI":"http://gateway.marvel.com/v1/public/comics/7612","date":"1979-03-10T00:00:00-0500","price":0.35,"thumbnail":"http://i.annihil.us/u/prod/marvel/i/mg/2/80/51ed86fec1adf/portrait_medium.jpg"},{"id":7611,"title":"Captain America (1968) #230","issueNumber":230.0,"resourceURI":"http://gateway.marvel.com/v1/public/comics/7611","date":"1979-02-10T00:00:00-0500","price":0.35,"thumbnail":"http://i.annihil.us/u/prod/marvel/i/mg/6/60/51ed873c3381b/portrait_medium.jpg"},{"id":7610,"title":"Captain America (1968) #229","issueNumber":229.0,"resourceURI":"http://gateway.marvel.com/v1/public/comics/7610","date":"1979-01-10T00:00:00-0500","price":0.35,"thumbnail":"http://i.annihil.us/u/prod/marvel/i/mg/6/b0/51ed877419b4a/portrait_medium.jpg"},{"id":7609,"title":"Captain America (1968) #228","issueNumber":228.0,"resourceURI":"http://gateway.marvel.com/v1/public/comics/7609","date":"1978-12-10T00:00:00-0500","price":0.35,"thumbnail":"http://i.annihil.us/u/prod/marvel/i/mg/9/70/51ed87ae70b36/portrait_medium.jpg"},{"id":7608,"title":"Captain America (1968) #227","issueNumber":227.0,"resourceURI":"http://gateway.marvel.com/v1/public/comics/7608","date":"1978-11-10T00:00:00-0500","price":0.35,"thumbnail":"http://i.annihil.us/u/prod/marvel/i/mg/f/80/56e6c32aebd7f/portrait_medium.jpg"},{"id":7607,"title":"Captain America (1968) #226","issueNumber":226.0,"resourceURI":"http://gateway.marvel.com/v1/public/comics/7607","date":"1978-10-10T00:00:00-0400","price":0.35,"thumbnail":"http://i.annihil.us/u/prod/marvel/i/mg/f/00/56e6c2aac2f1f/portrait_medium.jpg"},{"id":7606,"title":"Captain America (1968) #225","issueNumber":225.0,"resourceURI":"http://gateway.marvel.com/v1/public/comics/7606","date":"1978-09-10T00:00:00-0400","price":0.35,"thumbnail":"http://i.annihil.us/u/prod/marvel/i/mg/3/d0/51a8a84a55885/portrait_medium.jpg"},{"id":7605,"title":"Captain America (1968) #224","issueNumber":224.0,"resourceURI":"http://gateway.marvel.com/v1/public/comics/7605","date":"1978-08-10T00:00:00-0400","price":0.35,"thumbnail":"http://i.annihil.us/u/prod/marvel/i/mg/a/30/51ed87f18bc88/portrait_medium.jpg"},{"id":7604,"title":"Captain America (1968) #223","issueNumber":223.0,"resourceURI":"http://gateway.marvel.com/v1/public/comics/7604","date":"1978-07-10T00:00:00-0400","price":0.35,"thumbnail":"http://i.annihil.us/u/prod/marvel/i/mg/3/00/51ed882a44041/portrait_medium.jpg"},{"id":7603,"title":"Captain America (1968) #222","issueNumber":222.0,"resourceURI":"http://gateway.marvel.com/v1/public/comics/7603","date":"1978-06-10T00:00:00-0400","price":0.35,"thumbnail":"http://i.annihil.us/u/prod/marvel/i/mg/a/80/51ed8869f3cd9/portrait_medium.jpg"},{"id":7602,"title":"Captain America (1968) #221","issueNumber":221.0,"resourceURI":"http://gateway.marvel.com/v1/public/comics/7602","date":"1978-05-10T00:00:00-0400","price":0.35,"thumbnail":"http://i.annihil.us/u/prod/marvel/i/mg/3/70/599ef21f15131/portrait_medium.jpg"},{"id":7601,"title":"Captain America (1968) #220","issueNumber":220.0,"resourceURI":"http://gateway.marvel.com/v1/public/comics/7601","date":"1978-04-10T00:00:00-0500","price":0.35,"thumbnail":"http://i.annihil.us/u/prod/marvel/i/mg/6/b0/56e6c196107fc/portrait_medium.jpg"},{"id":7600,"title":"Captain America (1968) #219","issueNumber":219.0,"resourceURI":"http://gateway.marvel.com/v1/public/comics/7600","date":"1978-03-10T00:00:00-0500","price":0.35,"thumbnail":"http://i.annihil.us/u/prod/marvel/i/mg/8/f0/51ed88a290a1a/portrait_medium.jpg"},{"id":7599,"title":"Captain America (1968) #218","issueNumber":218.0,"resourceURI":"http://gateway.marvel.com/v1/public/comics/7599","date":"1978-02-10T00:00:00-0500","price":0.35,"thumbnail":"http://i.annihil.us/u/prod/marvel/i/mg/a/00/519fbc5887bc4/portrait_medium.jpg"},{"id":7598,"title":"Captain America (1968) #217","issueNumber":217.0,"resourceURI":"http://gateway.marvel.com/v1/public/comics/7598","date":"1978-01-10T00:00:00-0500","price":0.35,"thumbnail":"http://i.annihil.us/u/prod/marvel/i/mg/b/20/5143499746832/portrait_medium.jpg"},{"id":7597,"title":"Captain America (1968) #216","issueNumber":216.0,"resourceURI":"http://gateway.marvel.com/v1/public/comics/7597","date":"1977-12-10T00:00:00-0500","price":0.35,"thumbnail":"http://i.annihil.us/u/prod/marvel/i/mg/c/d0/51433b2867201/portrait_medium.jpg"},{"id":7596,"title":"Captain America (1968) #215","issueNumber":215.0,"resourceURI":"http://gateway.marvel.com/v1/public/comics/7596","date":"1977-11-10T00:00:00-0500","price":0.35,"thumbnail":"http://i.annihil.us/u/prod/marvel/i/mg/c/90/514333634202d/portrait_medium.jpg"},{"id":7595,"title":"Captain America (1968) #214","issueNumber":214.0,"resourceURI":"http://gateway.marvel.com/v1/public/comics/7595","date":"1977-10-10T00:00:00-0400","price":0.3,"thumbnail":"http://i.annihil.us/u/prod/marvel/i/mg/9/20/4bb6ee8641e01/portrait_medium.jpg"},{"id":7594,"title":"Captain America (1968) #213","issueNumber":213.0,"resourceURI":"http://gateway.marvel.com/v1/public/comics/7594","date":"1977-09-10T00:00:00-0400","price":0.3,"thumbnail":"http://i.annihil.us/u/prod/marvel/i/mg/f/50/4bb6ee8be605b/portrait_medium.jpg"},{"id":7593,"title":"Captain America (1968) #212","issueNumber":212.0,"resourceURI":"http://gateway.marvel.com/v1/public/comics/7593","date":"1977-08-10T00:00:00-0400","price":0.3,"thumbnail":"http://i.annihil.us/u/prod/marvel/i/mg/f/f0/4bb6ee9179dfb/portrait_medium.jpg"},{"id":7592,"title":"Captain America (1968) #211","issueNumber":211.0,"resourceURI":"http://gateway.marvel.com/v1/public/comics/7592","date":"1977-07-10T00:00:00-0400","price":0.3,"thumbnail":"http://i.annihil.us/u/prod/marvel/i/mg/c/90/4bb6ee971e1f3/portrait_medium.jpg"},{"id":7591,"title":"Captain America (1968) #210","issueNumber":210.0,"resourceURI":"http://gateway.marvel.com/v1/public/comics/7591","date":"1977-06-10T00:00:00-0400","price":0.3,"thumbnail":"http://i.annihil.us/u/prod/marvel/i/mg/c/e0/4bb6ee666e94a/portrait_medium.jpg"},{"id":7590,"title":"Captain America (1968) #209","issueNumber":209.0,"resourceURI":"http://gateway.marvel.com/v1/public/comics/7590","date":"1977-05-10T00:00:00-0400","price":0.3,"thumbnail":"http://i.annihil.us/u/prod/marvel/i/mg/f/60/4bb6ee9cb6c15/portrait_medium.jpg"},{"id":7589,"title":"Captain America (1968) #208","issueNumber":208.0,"resourceURI":"http://gateway.marvel.com/v1/public/comics/7589","date":"1977-04-10T00:00:00-0500","price":0.3,"thumbnail":"http://i.annihil.us/u/prod/marvel/i/mg/e/c0/4bb6eea26e0c2/portrait_medium.jpg"},{"id":7588,"title":"Captain America (1968) #207","issueNumber":207.0,"resourceURI":"http://gateway.marvel.com/v1/public/comics/7588","date":"1977-03-10T00:00:00-0500","price":0.3,"thumbnail":"http://i.annihil.us/u/prod/marvel/i/mg/f/00/4bb6eea80ac73/portrait_medium.jpg"},{"id":7587,"title":"Captain America (1968) #206","issueNumber":206.0,"resourceURI":"http://gateway.marvel.com/v1/public/comics/7587","date":"1977-02-10T00:00:00-0500","price":0.3,"thumbnail":"http://i.annihil.us/u/prod/marvel/i/mg/6/e0/56e6c09c34f83/portrait_medium.jpg"},{"id":7586,"title":"Captain America (1968) #205","issueNumber":205.0,"resourceURI":"http://gateway.marvel.com/v1/public/comics/7586","date":"1977-01-10T00:00:00-0500","price":0.3,"thumbnail":"http://i.annihil.us/u/prod/marvel/i/mg/5/20/4bb6eead9e3ba/portrait_medium.jpg"},{"id":7585,"title":"Captain America (1968) #204","issueNumber":204.0,"resourceURI":"http://gateway.marvel.com/v1/public/comics/7585","date":"1976-12-10T00:00:00-0500","price":0.3,"thumbnail":"http://i.annihil.us/u/prod/marvel/i/mg/f/00/4bb6eeb35e11f/portrait_medium.jpg"},{"id":7584,"title":"Captain America (1968) #203","issueNumber":203.0,"resourceURI":"http://gateway.marvel.com/v1/public/comics/7584","date":"1976-11-10T00:00:00-0500","price":0.3,"thumbnail":"http://i.annihil.us/u/prod/marvel/i/mg/f/20/4bb6eeb8c080d/portrait_medium.jpg"},{"id":7583,"title":"Captain America (1968) #202","issueNumber":202.0,"resourceURI":"http://gateway.marvel.com/v1/public/comics/7583","date":"1976-10-10T00:00:00-0400","price":0.3,"thumbnail":"http://i.annihil.us/u/prod/marvel/i/mg/f/60/4bb6eebe561c7/portrait_medium.jpg"},{"id":7582,"title":"Captain America (1968) #201","issueNumber":201.0,"resourceURI":"http://gateway.marvel.com/v1/public/comics/7582","date":"1976-09-10T00:00:00-0400","price":0.3,"thumbnail":"http://i.annihil.us/u/prod/marvel/i/mg/d/a0/59973c0611526/portrait_medium.jpg"},{"id":7581,"title":"Captain America (1968) #200","issueNumber":200.0,"resourceURI":"http://gateway.marvel.com/v1/public/comics/7581","date":"1976-08-10T00:00:00-0400","price":0.25,"thumbnail":"http://i.annihil.us/u/prod/marvel/i/mg/5/10/4bb6eec3cccc6/portrait_medium.jpg"},{"id":7580,"title":"Captain America (1968) #199","issueNumber":199.0,"resourceURI":"http://gateway.marvel.com/v1/public/comics/7580","date":"1976-07-10T00:00:00-0400","price":0.25,"thumbnail":"http://i.annihil.us/u/prod/marvel/i/mg/f/a0/4bb6ee6bc91e7/portrait_medium.jpg"},{"id":7579,"title":"Captain America (1968) #198","issueNumber":198.0,"resourceURI":"http://gateway.marvel.com/v1/public/comics/7579","date":"1976-06-10T00:00:00-0400","price":0.25,"thumbnail":"http://i.annihil.us/u/prod/marvel/i/mg/2/40/4bb6eec95bdb2/portrait_medium.jpg"},{"id":7578,"title":"Captain America (1968) #197","issueNumber":197.0,"resourceURI":"http://gateway.marvel.com/v1/public/comics/7578","date":"1976-05-10T00:00:00-0400","price":0.25,"thumbnail":"http://i.annihil.us/u/prod/marvel/i/mg/4/d0/4bb6eeceda50b/portrait_medium.jpg"},{"id":7577,"title":"Captain America (1968) #196","issueNumber":196.0,"resourceURI":"http://gateway.marvel.com/v1/public/comics/7577","date":"1976-04-10T00:00:00-0500","price":0.25,"thumbnail":"http://i.annihil.us/u/prod/marvel/i/mg/c/20/4bb6eed4b1923/portrait_medium.jpg"},{"id":7576,"title":"Captain America (1968) #195","issueNumber":195.0,"resourceURI":"http://gateway.marvel.com/v1/public/comics/7576","date":"1976-03-10T00:00:00-0500","price":0.25,"thumbnail":"http://i.annihil.us/u/prod/marvel/i/mg/f/50/4bb6eeda81c92/portrait_medium.jpg"},{"id":7575,"title":"Captain America (1968) #194","issueNumber":194.0,"resourceURI":"http://gateway.marvel.com/v1/public/comics/7575","date":"1976-02-10T00:00:00-0500","price":0.25,"thumbnail":"http://i.annihil.us/u/prod/marvel/i/mg/c/50/4bb6eee02397b/portrait_medium.jpg"},{"id":7574,"title":"Captain America (1968) #193","issueNumber":193.0,"resourceURI":"http://gateway.marvel.com/v1/public/comics/7574","date":"1976-01-10T00:00:00-0500","price":0.25,"thumbnail":"http://i.annihil.us/u/prod/marvel/i/mg/c/00/4bb6eee5d2331/portrait_medium.jpg"},{"id":7573,"title":"Captain America (1968) #192","issueNumber":192.0,"resourceURI":"http://gateway.marvel.com/v1/public/comics/7573","date":"1975-12-10T00:00:00-0500","price":0.25,"thumbnail":"http://i.annihil.us/u/prod/marvel/i/mg/6/e0/56e6bf06d5961/portrait_medium.jpg"},{"id":7572,"title":"Captain America (1968) #191","issueNumber":191.0,"resourceURI":"http://gateway.marvel.com/v1/public/comics/7572","date":"1975-11-10T00:00:00-0500","price":0.25,"thumbnail":"http://i.annihil.us/u/prod/marvel/i/mg/d/30/56e6bea861ff9/portrait_medium.jpg"},{"id":7571,"title":"Captain America (1968) #190","issueNumber":190.0,"resourceURI":"http://gateway.marvel.com/v1/public/comics/7571","date":"1975-10-10T00:00:00-0400","price":0.25,"thumbnail":"http://i.annihil.us/u/prod/marvel/i/mg/f/90/56e6bc6beb4f4/portrait_medium.jpg"},{"id":7570,"title":"Captain America (1968) #189","issueNumber":189.0,"resourceURI":"http://gateway.marvel.com/v1/public/comics/7570","date":"1975-09-10T00:00:00-0400","price":0.25,"thumbnail":"http://i.annihil.us/u/prod/marvel/i/mg/9/a0/56e6bb6b0891e/portrait_medium.jpg"},{"id":7569,"title":"Captain America (1968) #188","issueNumber":188.0,"resourceURI":"http://gateway.marvel.com/v1/public/comics/7569","date":"1975-08-10T00:00:00-0400","price":0.25,"thumbnail":"http://i.annihil.us/u/prod/marvel/i/mg/9/70/56e6b9ac56d11/portrait_medium.jpg"},{"id":7568,"title":"Captain America (1968) #187","issueNumber":187.0,"resourceURI":"http://gateway.marvel.com/v1/public/comics/7568","date":"1975-07-10T00:00:00-0400","price":0.25,"thumbnail":"http://i.annihil.us/u/prod/marvel/i/mg/3/d0/56e6b87b15706/portrait_medium.jpg"},{"id":7567,"title":"Captain America (1968) #186","issueNumber":186.0,"resourceURI":"http://gateway.marvel.com/v1/public/comics/7567","date":"1975-06-10T00:00:00-0400","price":0.25,"thumbnail":"http://i.annihil.us/u/prod/marvel/i/mg/2/70/4bb6eeeb7bd19/portrait_medium.jpg"},{"id":7566,"title":"Captain America (1968) #185","issueNumber":185.0,"resourceURI":"http://gateway.marvel.com/v1/public/comics/7566","date":"1975-05-10T00:00:00-0400","price":0.25,"thumbnail":"http://i.annihil.us/u/prod/marvel/i/mg/9/60/4bb6f7406fc43/portrait_medium.jpg"},{"id":7565,"title":"Captain America (1968) #184","issueNumber":184.0,"resourceURI":"http://gateway.marvel.com/v1/public/comics/7565","date":"1975-04-10T00:00:00-0400","price":0.25,"thumbnail":"http://i.annihil.us/u/prod/marvel/i/mg/6/e0/59b98a1be7705/portrait_medium.jpg"},{"id":7564,"title":"Captain America (1968) #183","issueNumber":183.0,"resourceURI":"http://gateway.marvel.com/v1/public/comics/7564","date":"1975-03-10T00:00:00-0400","price":0.25,"thumbnail":"http://i.annihil.us/u/prod/marvel/i/mg/4/80/59b963c36a987/portrait_medium.jpg"},{"id":7563,"title":"Captain America (1968) #182","issueNumber":182.0,"resourceURI":"http://gateway.marvel.com/v1/public/comics/7563","date":"1975-02-10T00:00:00-0500","price":0.25,"thumbnail":"http://i.annihil.us/u/prod/marvel/i/mg/d/40/59b9625feaff5/portrait_medium.jpg"},{"id":7562,"title":"Captain America (1968) #181","issueNumber":181.0,"resourceURI":"http://gateway.marvel.com/v1/public/comics/7562","date":"1975-01-10T00:00:00-0500","price":0.25,"thumbnail":"http://i.annihil.us/u/prod/marvel/i/mg/1/20/59b961148519e/portrait_medium.jpg"},{"id":7561,"title":"Captain America (1968) #180","issueNumber":180.0,"resourceURI":"http://gateway.marvel.com/v1/public/comics/7561","date":"1974-12-10T00:00:00-0500","price":0.25,"thumbnail":"http://i.annihil.us/u/prod/marvel/i/mg/7/50/59b95c637c49c/portrait_medium.jpg"},{"id":7560,"title":"Captain America (1968) #179","issueNumber":179.0,"resourceURI":"http://gateway.marvel.com/v1/public/comics/7560","date":"1974-11-10T00:00:00-0500","price":0.25,"thumbnail":"http://i.annihil.us/u/prod/marvel/i/mg/c/03/59b95b1071936/portrait_medium.jpg"},{"id":7559,"title":"Captain America (1968) #178","issueNumber":178.0,"resourceURI":"http://gateway.marvel.com/v1/public/comics/7559","date":"1974-10-10T00:00:00-0400","price":0.25,"thumbnail":"http://i.annihil.us/u/prod/marvel/i/mg/3/f0/59b959b7d3700/portrait_medium.jpg"},{"id":7558,"title":"Captain America (1968) #177","issueNumber":177.0,"resourceURI":"http://gateway.marvel.com/v1/public/comics/7558","date":"1974-09-10T00:00:00-0400","price":0.25,"thumbnail":"http://i.annihil.us/u/prod/marvel/i/mg/1/60/59b95823292e8/portrait_medium.jpg"},{"id":7557,"title":"Captain America (1968) #176","issueNumber":176.0,"resourceURI":"http://gateway.marvel.com/v1/public/comics/7557","date":"1974-08-10T00:00:00-0400","price":0.25,"thumbnail":"http://i.annihil.us/u/prod/marvel/i/mg/4/40/59b9566475aa7/portrait_medium.jpg"},{"id":7556,"title":"Captain America (1968) #175","issueNumber":175.0,"resourceURI":"http://gateway.marvel.com/v1/public/comics/7556","date":"1974-07-10T00:00:00-0400","price":0.25,"thumbnail":"http://i.annihil.us/u/prod/marvel/i/mg/a/10/4bb6f9378e65a/portrait_medium.jpg"},{"id":7555,"title":"Captain America (1968) #174","issueNumber":174.0,"resourceURI":"http://gateway.marvel.com/v1/public/comics/7555","date":"1974-06-10T00:00:00-0400","price":0.25,"thumbnail":"http://i.annihil.us/u/prod/marvel/i/mg/8/b0/4bb6f93d001b3/portrait_medium.jpg"},{"id":7554,"title":"Captain America (1968) #173","issueNumber":173.0,"resourceURI":"http://gateway.marvel.com/v1/public/comics/7554","date":"1974-05-10T00:00:00-0400","price":0.25,"thumbnail":"http://i.annihil.us/u/prod/marvel/i/mg/9/60/4bb6f9425e24b/portrait_medium.jpg"},{"id":7553,"title":"Captain America (1968) #172","issueNumber":172.0,"resourceURI":"http://gateway.marvel.com/v1/public/comics/7553","date":"1974-04-10T00:00:00-0400","price":0.2,"thumbnail":"http://i.annihil.us/u/prod/marvel/i/mg/9/b0/4bb6f95c921c6/portrait_medium.jpg"},{"id":7552,"title":"Captain America (1968) #171","issueNumber":171.0,"resourceURI":"http://gateway.marvel.com/v1/public/comics/7552","date":"1974-03-10T00:00:00-0400","price":0.2,"thumbnail":"http://i.annihil.us/u/prod/marvel/i/mg/9/e0/4bb6f961d74b8/portrait_medium.jpg"},{"id":7551,"title":"Captain America (1968) #170","issueNumber":170.0,"resourceURI":"http://gateway.marvel.com/v1/public/comics/7551","date":"1974-02-10T00:00:00-0400","price":0.2,"thumbnail":"http://i.annihil.us/u/prod/marvel/i/mg/3/b0/4bb6f96722228/portrait_medium.jpg"},{"id":7550,"title":"Captain America (1968) #169","issueNumber":169.0,"resourceURI":"http://gateway.marvel.com/v1/public/comics/7550","date":"1974-01-10T00:00:00-0400","price":0.2,"thumbnail":"http://i.annihil.us/u/prod/marvel/i/mg/a/20/4bb6f947d9b91/portrait_medium.jpg"},{"id":7549,"title":"Captain America (1968) #168","issueNumber":168.0,"resourceURI":"http://gateway.marvel.com/v1/public/comics/7549","date":"1973-12-10T00:00:00-0500","price":0.2,"thumbnail":"http://i.annihil.us/u/prod/marvel/i/mg/6/90/56e33a8d069e1/portrait_medium.jpg"},{"id":7548,"title":"Captain America (1968) #167","issueNumber":167.0,"resourceURI":"http://gateway.marvel.com/v1/public/comics/7548","date":"1973-11-10T00:00:00-0500","price":0.2,"thumbnail":"http://i.annihil.us/u/prod/marvel/i/mg/8/c0/56e33a0e1ba47/portrait_medium.jpg"},{"id":7547,"title":"Captain America (1968) #166","issueNumber":166.0,"resourceURI":"http://gateway.marvel.com/v1/public/comics/7547","date":"1973-10-10T00:00:00-0400","price":0.2,"thumbnail":"http://i.annihil.us/u/prod/marvel/i/mg/4/00/56e33992f208e/portrait_medium.jpg"},{"id":7546,"title":"Captain America (1968) #165","issueNumber":165.0,"resourceURI":"http://gateway.marvel.com/v1/public/comics/7546","date":"1973-09-10T00:00:00-0400","price":0.2,"thumbnail":"http://i.annihil.us/u/prod/marvel/i/mg/7/10/56e338b096d9d/portrait_medium.jpg"},{"id":7545,"title":"Captain America (1968) #164","issueNumber":164.0,"resourceURI":"http://gateway.marvel.com/v1/public/comics/7545","date":"1973-08-10T00:00:00-0400","price":0.2,"thumbnail":"http://i.annihil.us/u/prod/marvel/i/mg/3/50/56e338341d24d/portrait_medium.jpg"},{"id":7544,"title":"Captain America (1968) #163","issueNumber":163.0,"resourceURI":"http://gateway.marvel.com/v1/public/comics/7544","date":"1973-07-10T00:00:00-0400","price":0.2,"thumbnail":"http://i.annihil.us/u/prod/marvel/i/mg/8/e0/56e337ce1c2b0/portrait_medium.jpg"},{"id":7543,"title":"Captain America (1968) #162","issueNumber":162.0,"resourceURI":"http://gateway.marvel.com/v1/public/comics/7543","date":"1973-06-10T00:00:00-0400","price":0.2,"thumbnail":"http://i.annihil.us/u/prod/marvel/i/mg/9/a0/56e3375eef23b/portrait_medium.jpg"},{"id":7542,"title":"Captain America (1968) #161","issueNumber":161.0,"resourceURI":"http://gateway.marvel.com/v1/public/comics/7542","date":"1973-05-10T00:00:00-0400","price":0.2,"thumbnail":"http://i.annihil.us/u/prod/marvel/i/mg/9/50/56e336c453cbd/portrait_medium.jpg"},{"id":7541,"title":"Captain America (1968) #160","issueNumber":160.0,"resourceURI":"http://gateway.marvel.com/v1/public/comics/7541","date":"1973-04-10T00:00:00-0500","price":0.2,"thumbnail":"http://i.annihil.us/u/prod/marvel/i/mg/e/03/56e3357f37263/portrait_medium.jpg"},{"id":7540,"title":"Captain America (1968) #159","issueNumber":159.0,"resourceURI":"http://gateway.marvel.com/v1/public/comics/7540","date":"1973-03-10T00:00:00-0500","price":0.2,"thumbnail":"http://i.annihil.us/u/prod/marvel/i/mg/3/30/56e334ee16142/portrait_medium.jpg"},{"id":7539,"title":"Captain America (1968) #158","issueNumber":158.0,"resourceURI":"http://gateway.marvel.com/v1/public/comics/7539","date":"1973-02-10T00:00:00-0500","price":0.2,"thumbnail":"http://i.annihil.us/u/prod/marvel/i/mg/d/30/56e3348341026/portrait_medium.jpg"},{"id":7538,"title":"Captain America (1968) #157","issueNumber":157.0,"resourceURI":"http://gateway.marvel.com/v1/public/comics/7538","date":"1973-01-10T00:00:00-0500","price":0.2,"thumbnail":"http://i.annihil.us/u/prod/marvel/i/mg/9/70/56e333fcf1c64/portrait_medium.jpg"},{"id":7537,"title":"Captain America (1968) #156","issueNumber":156.0,"resourceURI":"http://gateway.marvel.com/v1/public/comics/7537","date":"1972-12-10T00:00:00-0500","price":0.2,"thumbnail":"http://i.annihil.us/u/prod/marvel/i/mg/3/c0/56e3339642e7a/portrait_medium.jpg"},{"id":7536,"title":"Captain America (1968) #155","issueNumber":155.0,"resourceURI":"http://gateway.marvel.com/v1/public/comics/7536","date":"1972-11-10T00:00:00-0500","price":0.2,"thumbnail":"http://i.annihil.us/u/prod/marvel/i/mg/f/d0/56e333025d215/portrait_medium.jpg"},{"id":7535,"title":"Captain America (1968) #154","issueNumber":154.0,"resourceURI":"http://gateway.marvel.com/v1/public/comics/7535","date":"1972-10-10T00:00:00-0400","price":0.2,"thumbnail":"http://i.annihil.us/u/prod/marvel/i/mg/1/30/56e3323988e45/portrait_medium.jpg"},{"id":7534,"title":"Captain America (1968) #153","issueNumber":153.0,"resourceURI":"http://gateway.marvel.com/v1/public/comics/7534","date":"1972-09-10T00:00:00-0400","price":0.2,"thumbnail":"http://i.annihil.us/u/prod/marvel/i/mg/8/b0/56e330aab4b28/portrait_medium.jpg"},{"id":7533,"title":"Captain America (1968) #152","issueNumber":152.0,"resourceURI":"http://gateway.marvel.com/v1/public/comics/7533","date":"1972-08-10T00:00:00-0400","price":0.2,"thumbnail":"http://i.annihil.us/u/prod/marvel/i/mg/4/00/56e32fd763718/portrait_medium.jpg"},{"id":7532,"title":"Captain America (1968) #151","issueNumber":151.0,"resourceURI":"http://gateway.marvel.com/v1/public/comics/7532","date":"1972-07-10T00:00:00-0400","price":0.2,"thumbnail":"http://i.annihil.us/u/prod/marvel/i/mg/d/b0/5995f00115593/portrait_medium.jpg"},{"id":7531,"title":"Captain America (1968) #150","issueNumber":150.0,"resourceURI":"http://gateway.marvel.com/v1/public/comics/7531","date":"1972-06-10T00:00:00-0400","price":0.2,"thumbnail":"http://i.annihil.us/u/prod/marvel/i/mg/3/20/56e32d1876a01/portrait_medium.jpg"},{"id":7530,"title":"Captain America (1968) #149","issueNumber":149.0,"resourceURI":"http://gateway.marvel.com/v1/public/comics/7530","date":"1972-05-10T00:00:00-0400","price":0.2,"thumbnail":"http://i.annihil.us/u/prod/marvel/i/mg/b/f0/56e32cb03a5ef/portrait_medium.jpg"},{"id":7529,"title":"Captain America (1968) #148","issueNumber":148.0,"resourceURI":"http://gateway.marvel.com/v1/public/comics/7529","date":"1972-04-10T00:00:00-0500","price":0.2,"thumbnail":"http://i.annihil.us/u/prod/marvel/i/mg/9/c0/5995dab135e5e/portrait_medium.jpg"},{"id":7528,"title":"Captain America (1968) #147","issueNumber":147.0,"resourceURI":"http://gateway.marvel.com/v1/public/comics/7528","date":"1972-03-10T00:00:00-0500","price":0.2,"thumbnail":"http://i.annihil.us/u/prod/marvel/i/mg/6/00/56e32bd2953a0/portrait_medium.jpg"},{"id":7527,"title":"Captain America (1968) #146","issueNumber":146.0,"resourceURI":"http://gateway.marvel.com/v1/public/comics/7527","date":"1972-02-10T00:00:00-0500","price":0.2,"thumbnail":"http://i.annihil.us/u/prod/marvel/i/mg/2/40/5995b48f88757/portrait_medium.jpg"},{"id":7526,"title":"Captain America (1968) #145","issueNumber":145.0,"resourceURI":"http://gateway.marvel.com/v1/public/comics/7526","date":"1972-01-10T00:00:00-0500","price":0.2,"thumbnail":"http://i.annihil.us/u/prod/marvel/i/mg/8/00/5995a9f956af8/portrait_medium.jpg"},{"id":7525,"title":"Captain America (1968) #144","issueNumber":144.0,"resourceURI":"http://gateway.marvel.com/v1/public/comics/7525","date":"1971-12-10T00:00:00-0500","price":0.2,"thumbnail":"http://i.annihil.us/u/prod/marvel/i/mg/9/70/5995a11b2d9ae/portrait_medium.jpg"},{"id":7524,"title":"Captain America (1968) #143","issueNumber":143.0,"resourceURI":"http://gateway.marvel.com/v1/public/comics/7524","date":"1971-11-10T00:00:00-0500","price":0.25,"thumbnail":"http://i.annihil.us/u/prod/marvel/i/mg/3/a0/56e32b193a677/portrait_medium.jpg"},{"id":7523,"title":"Captain America (1968) #142","issueNumber":142.0,"resourceURI":"http://gateway.marvel.com/v1/public/comics/7523","date":"1971-10-10T00:00:00-0400","price":0.15,"thumbnail":"http://i.annihil.us/u/prod/marvel/i/mg/4/80/5994a9f78e161/portrait_medium.jpg"},{"id":7522,"title":"Captain America (1968) #141","issueNumber":141.0,"resourceURI":"http://gateway.marvel.com/v1/public/comics/7522","date":"1971-09-10T00:00:00-0400","price":0.15,"thumbnail":"http://i.annihil.us/u/prod/marvel/i/mg/e/90/5994a46597256/portrait_medium.jpg"},{"id":7521,"title":"Captain America (1968) #140","issueNumber":140.0,"resourceURI":"http://gateway.marvel.com/v1/public/comics/7521","date":"1971-08-10T00:00:00-0400","price":0.15,"thumbnail":"http://i.annihil.us/u/prod/marvel/i/mg/a/10/5995f5f4d5bd0/portrait_medium.jpg"},{"id":7520,"title":"Captain America (1968) #139","issueNumber":139.0,"resourceURI":"http://gateway.marvel.com/v1/public/comics/7520","date":"1971-07-10T00:00:00-0400","price":0.15,"thumbnail":"http://i.annihil.us/u/prod/marvel/i/mg/4/20/5995f4f2941c2/portrait_medium.jpg"},{"id":7519,"title":"Captain America (1968) #138","issueNumber":138.0,"resourceURI":"http://gateway.marvel.com/v1/public/comics/7519","date":"1971-06-10T00:00:00-0400","price":0.15,"thumbnail":"http://i.annihil.us/u/prod/marvel/i/mg/6/d0/5995f418dba06/portrait_medium.jpg"},{"id":7518,"title":"Captain America (1968) #137","issueNumber":137.0,"resourceURI":"http://gateway.marvel.com/v1/public/comics/7518","date":"1971-05-10T00:00:00-0400","price":0.15,"thumbnail":"http://i.annihil.us/u/prod/marvel/i/mg/3/e0/5995f2b50f183/portrait_medium.jpg"},{"id":7517,"title":"Captain America (1968) #136","issueNumber":136.0,"resourceURI":"http://gateway.marvel.com/v1/public/comics/7517","date":"1971-04-10T00:00:00-0500","price":0.15,"thumbnail":"http://i.annihil.us/u/prod/marvel/i/mg/3/c0/5995f186c21a3/portrait_medium.jpg"},{"id":7516,"title":"Captain America (1968) #135","issueNumber":135.0,"resourceURI":"http://gateway.marvel.com/v1/public/comics/7516","date":"1971-03-10T00:00:00-0500","price":0.15,"thumbnail":"http://i.annihil.us/u/prod/marvel/i/mg/a/10/5995f05d6dbb7/portrait_medium.jpg"},{"id":7515,"title":"Captain America (1968) #134","issueNumber":134.0,"resourceURI":"http://gateway.marvel.com/v1/public/comics/7515","date":"1971-02-10T00:00:00-0500","price":0.15,"thumbnail":"http://i.annihil.us/u/prod/marvel/i/mg/7/90/5995eef74319d/portrait_medium.jpg"},{"id":7514,"title":"Captain America (1968) #133","issueNumber":133.0,"resourceURI":"http://gateway.marvel.com/v1/public/comics/7514","date":"1971-01-10T00:00:00-0500","price":0.15,"thumbnail":"http://i.annihil.us/u/prod/marvel/i/mg/6/f0/5995ed3b1791b/portrait_medium.jpg"},{"id":7513,"title":"Captain America (1968) #132","issueNumber":132.0,"resourceURI":"http://gateway.marvel.com/v1/public/comics/7513","date":"1970-12-10T00:00:00-0500","price":0.15,"thumbnail":"http://i.annihil.us/u/prod/marvel/i/mg/a/c0/5995eb4df39f8/portrait_medium.jpg"},{"id":7512,"title":"Captain America (1968) #131","issueNumber":131.0,"resourceURI":"http://gateway.marvel.com/v1/public/comics/7512","date":"1970-11-10T00:00:00-0500","price":0.15,"thumbnail":"http://i.annihil.us/u/prod/marvel/i/mg/1/d0/5995e96191d76/portrait_medium.jpg"},{"id":7511,"title":"Captain America (1968) #130","issueNumber":130.0,"resourceURI":"http://gateway.marvel.com/v1/public/comics/7511","date":"1970-10-10T00:00:00-0400","price":0.15,"thumbnail":"http://i.annihil.us/u/prod/marvel/i/mg/3/50/56e326bd13285/portrait_medium.jpg"},{"id":7510,"title":"Captain America (1968) #129","issueNumber":129.0,"resourceURI":"http://gateway.marvel.com/v1/public/comics/7510","date":"1970-09-10T00:00:00-0400","price":0.15,"thumbnail":"http://i.annihil.us/u/prod/marvel/i/mg/c/30/56e3255baf6ca/portrait_medium.jpg"},{"id":7509,"title":"Captain America (1968) #128","issueNumber":128.0,"resourceURI":"http://gateway.marvel.com/v1/public/comics/7509","date":"1970-08-10T00:00:00-0400","price":0.15,"thumbnail":"http://i.annihil.us/u/prod/marvel/i/mg/9/70/56e3247eda51f/portrait_medium.jpg"},{"id":7508,"title":"Captain America (1968) #127","issueNumber":127.0,"resourceURI":"http://gateway.marvel.com/v1/public/comics/7508","date":"1970-07-10T00:00:00-0400","price":0.15,"thumbnail":"http://i.annihil.us/u/prod/marvel/i/mg/9/50/56e321e8c2a5f/portrait_medium.jpg"},{"id":7507,"title":"Captain America (1968) #126","issueNumber":126.0,"resourceURI":"http://gateway.marvel.com/v1/public/comics/7507","date":"1970-06-10T00:00:00-0400","price":0.15,"thumbnail":"http://i.annihil.us/u/prod/marvel/i/mg/6/30/56e320f61c3f4/portrait_medium.jpg"},{"id":7506,"title":"Captain America (1968) #125","issueNumber":125.0,"resourceURI":"http://gateway.marvel.com/v1/public/comics/7506","date":"1970-05-10T00:00:00-0400","price":0.15,"thumbnail":"http://i.annihil.us/u/prod/marvel/i/mg/1/00/56e320766666e/portrait_medium.jpg"},{"id":7505,"title":"Captain America (1968) #124","issueNumber":124.0,"resourceURI":"http://gateway.marvel.com/v1/public/comics/7505","date":"1970-04-10T00:00:00-0500","price":0.15,"thumbnail":"http://i.annihil.us/u/prod/marvel/i/mg/1/b0/4bb5fab171fcb/portrait_medium.jpg"},{"id":7504,"title":"Captain America (1968) #123","issueNumber":123.0,"resourceURI":"http://gateway.marvel.com/v1/public/comics/7504","date":"1970-03-10T00:00:00-0500","price":0.15,"thumbnail":"http://i.annihil.us/u/prod/marvel/i/mg/c/20/4bb5fab73646a/portrait_medium.jpg"},{"id":7503,"title":"Captain America (1968) #122","issueNumber":122.0,"resourceURI":"http://gateway.marvel.com/v1/public/comics/7503","date":"1970-02-10T00:00:00-0500","price":0.15,"thumbnail":"http://i.annihil.us/u/prod/marvel/i/mg/1/d0/4bb5fbb63bd3c/portrait_medium.jpg"},{"id":7502,"title":"Captain America (1968) #121","issueNumber":121.0,"resourceURI":"http://gateway.marvel.com/v1/public/comics/7502","date":"1970-01-10T00:00:00-0500","price":0.15,"thumbnail":"http://i.annihil.us/u/prod/marvel/i/mg/1/e0/4bb5fbbbc40d9/portrait_medium.jpg"},{"id":7501,"title":"Captain America (1968) #120","issueNumber":120.0,"resourceURI":"http://gateway.marvel.com/v1/public/comics/7501","date":"1969-12-10T00:00:00-0500","price":0.15,"thumbnail":"http://i.annihil.us/u/prod/marvel/i/mg/e/e0/4bb5fbc10eb49/portrait_medium.jpg"},{"id":7500,"title":"Captain America (1968) #119","issueNumber":119.0,"resourceURI":"http://gateway.marvel.com/v1/public/comics/7500","date":"1969-11-10T00:00:00-0500","price":0.15,"thumbnail":"http://i.annihil.us/u/prod/marvel/i/mg/b/f0/4bb5fbc6b1940/portrait_medium.jpg"},{"id":7499,"title":"Captain America (1968) #118","issueNumber":118.0,"resourceURI":"http://gateway.marvel.com/v1/public/comics/7499","date":"1969-10-10T00:00:00-0400","price":0.15,"thumbnail":"http://i.annihil.us/u/prod/marvel/i/mg/2/50/4bb5fbcc6cc94/portrait_medium.jpg"},{"id":7498,"title":"Captain America (1968) #117","issueNumber":117.0,"resourceURI":"http://gateway.marvel.com/v1/public/comics/7498","date":"1969-09-10T00:00:00-0400","price":0.15,"thumbnail":"http://i.annihil.us/u/prod/marvel/i/mg/f/60/4bb5fbd17ee28/portrait_medium.jpg"},{"id":7497,"title":"Captain America (1968) #116","issueNumber":116.0,"resourceURI":"http://gateway.marvel.com/v1/public/comics/7497","date":"1969-08-10T00:00:00-0400","price":0.15,"thumbnail":"http://i.annihil.us/u/prod/marvel/i/mg/f/b0/4bb5fbd6e673f/portrait_medium.jpg"},{"id":7496,"title":"Captain America (1968) #115","issueNumber":115.0,"resourceURI":"http://gateway.marvel.com/v1/public/comics/7496","date":"1969-07-10T00:00:00-0400","price":0.12,"thumbnail":"http://i.annihil.us/u/prod/marvel/i/mg/2/10/4bb5fdcd9f1a1/portrait_medium.jpg"},{"id":7495,"title":"Captain America (1968) #114","issueNumber":114.0,"resourceURI":"http://gateway.marvel.com/v1/public/comics/7495","date":"1969-06-10T00:00:00-0400","price":0.12,"thumbnail":"http://i.annihil.us/u/prod/marvel/i/mg/9/50/4bb5ff380a672/portrait_medium.jpg"},{"id":7494,"title":"Captain America (1968) #113","issueNumber":113.0,"resourceURI":"http://gateway.marvel.com/v1/public/comics/7494","date":"1969-05-10T00:00:00-0400","price":0.12,"thumbnail":"http://i.annihil.us/u/prod/marvel/i/mg/3/a0/54b3d69a68603/portrait_medium.jpg"},{"id":7493,"title":"Captain America (1968) #112","issueNumber":112.0,"resourceURI":"http://gateway.marvel.com/v1/public/comics/7493","date":"1969-04-10T00:00:00-0500","price":0.12,"thumbnail":"http://i.annihil.us/u/prod/marvel/i/mg/6/e0/56e31f777c73a/portrait_medium.jpg"},{"id":7492,"title":"Captain America (1968) #111","issueNumber":111.0,"resourceURI":"http://gateway.marvel.com/v1/public/comics/7492","date":"1969-03-10T00:00:00-0500","price":0.12,"thumbnail":"http://i.annihil.us/u/prod/marvel/i/mg/9/30/56e31e66d11fa/portrait_medium.jpg"},{"id":7491,"title":"Captain America (1968) #110","issueNumber":110.0,"resourceURI":"http://gateway.marvel.com/v1/public/comics/7491","date":"1969-02-10T00:00:00-0500","price":0.12,"thumbnail":"http://i.annihil.us/u/prod/marvel/i/mg/9/e0/59946fc3ddc50/portrait_medium.jpg"},{"id":7490,"title":"Captain America (1968) #109","issueNumber":109.0,"resourceURI":"http://gateway.marvel.com/v1/public/comics/7490","date":"1969-01-10T00:00:00-0500","price":0.12,"thumbnail":"http://i.annihil.us/u/prod/marvel/i/mg/a/80/59946e94a4fed/portrait_medium.jpg"},{"id":7489,"title":"Captain America (1968) #108","issueNumber":108.0,"resourceURI":"http://gateway.marvel.com/v1/public/comics/7489","date":"1968-12-10T00:00:00-0500","price":0.12,"thumbnail":"http://i.annihil.us/u/prod/marvel/i/mg/3/f0/59946d37056ca/portrait_medium.jpg"},{"id":7488,"title":"Captain America (1968) #107","issueNumber":107.0,"resourceURI":"http://gateway.marvel.com/v1/public/comics/7488","date":"1968-11-10T00:00:00-0500","price":0.12,"thumbnail":"http://i.annihil.us/u/prod/marvel/i/mg/1/30/59946b96b9122/portrait_medium.jpg"},{"id":7487,"title":"Captain America (1968) #106","issueNumber":106.0,"resourceURI":"http://gateway.marvel.com/v1/public/comics/7487","date":"1968-10-10T00:00:00-0400","price":0.12,"thumbnail":"http://i.annihil.us/u/prod/marvel/i/mg/3/e0/59946a411cf93/portrait_medium.jpg"},{"id":7486,"title":"Captain America (1968) #105","issueNumber":105.0,"resourceURI":"http://gateway.marvel.com/v1/public/comics/7486","date":"1968-09-10T00:00:00-0400","price":0.12,"thumbnail":"http://i.annihil.us/u/prod/marvel/i/mg/4/70/5994695dbc662/portrait_medium.jpg"},{"id":7485,"title":"Captain America (1968) #104","issueNumber":104.0,"resourceURI":"http://gateway.marvel.com/v1/public/comics/7485","date":"1968-08-10T00:00:00-0400","price":0.12,"thumbnail":"http://i.annihil.us/u/prod/marvel/i/mg/e/00/5994680408d42/portrait_medium.jpg"},{"id":7484,"title":"Captain America (1968) #103","issueNumber":103.0,"resourceURI":"http://gateway.marvel.com/v1/public/comics/7484","date":"1968-07-10T00:00:00-0400","price":0.12,"thumbnail":"http://i.annihil.us/u/prod/marvel/i/mg/1/d0/5994675a697f2/portrait_medium.jpg"},{"id":7483,"title":"Captain America (1968) #102","issueNumber":102.0,"resourceURI":"http://gateway.marvel.com/v1/public/comics/7483","date":"1968-06-10T00:00:00-0400","price":0.12,"thumbnail":"http://i.annihil.us/u/prod/marvel/i/mg/4/30/599465dc459a2/portrait_medium.jpg"},{"id":7482,"title":"Captain America (1968) #101","issueNumber":101.0,"resourceURI":"http://gateway.marvel.com/v1/public/comics/7482","date":"1968-05-10T00:00:00-0400","price":0.12,"thumbnail":"http://i.annihil.us/u/prod/marvel/i/mg/7/70/599464d5e85bd/portrait_medium.jpg"},{"id":7481,"title":"Captain America (1968) #100","issueNumber":100.0,"resourceURI":"http://gateway.marvel.com/v1/public/comics/7481","date":"1968-04-10T00:00:00-0500","price":0.12,"thumbnail":"http://i.annihil.us/u/prod/marvel/i/mg/3/50/5994604e20b1e/portrait_medium.jpg"}]}