{"id":"20226","title":"Star Wars: Tales Of The Jedi (1993 - 1994)","description":"","resourceURI":"http://gateway.marvel.com/v1/public/series/20226","startYear":1993,"endYear":1994,"thumbnail":"http://i.annihil.us/u/prod/marvel/i/mg/b/40/image_not_available/portrait_medium.jpg","issueCount":5,"issues":[{"id":54570,"title":"Star Wars: Tales Of The Jedi (1993) #5","issueNumber":5.0,"resourceURI":"http://gateway.marvel.com/v1/public/comics/54570","date":"1994-02-01T00:00:00-0500","price":0.0,"thumbnail":"http://i.annihil.us/u/prod/marvel/i/mg/f/70/552fdd5bf35dc/portrait_medium.jpg"},{"id":54569,"title":"Star Wars: Tales Of The Jedi (1993) #4","issueNumber":4.0,"resourceURI":"http://gateway.marvel.com/v1/public/comics/54569","date":"1994-01-01T00:00:00-0500","price":0.0,"thumbnail":"http://i.annihil.us/u/prod/marvel/i/mg/c/60/552fdcba458f2/portrait_medium.jpg"},{"id":54568,"title":"Star Wars: Tales Of The Jedi (1993) #3","issueNumber":3.0,"resourceURI":"http://gateway.marvel.com/v1/public/comics/54568","date":"1993-12-01T00:00:00-0500","price":0.0,"thumbnail":"http://i.annihil.us/u/prod/marvel/i/mg/9/30/552fdc52b45f1/portrait_medium.jpg"},{"id":54567,"title":"Star Wars: Tales Of The Jedi (1993) #2","issueNumber":2.0,"resourceURI":"http://gateway.marvel.com/v1/public/comics/54567","date":"1993-11-15T00:00:00-0500","price":0.0,"thumbnail":"http://i.annihil.us/u/prod/marvel/i/mg/f/90/552fdbd583cde/portrait_medium.jpg"},{"id":54566,"title":"Star Wars: Tales Of The Jedi (1993) #1","issueNumber":1.0,"resourceURI":"http://gateway.marvel.com/v1/public/comics/54566","date":"1993-10-01T00:00:00-0400","price":0.0,"thumbnail":"http://i.annihil.us/u/prod/marvel/i/mg/c/10/552fdb6b801dc/portrait_medium.jpg"}]}