{"id":"2089","title":"Vampire Tales (1973 - 1975)","description":"","resourceURI":"http://gateway.marvel.com/v1/public/series/2089","startYear":1973,"endYear":1975,"thumbnail":"http://i.annihil.us/u/prod/marvel/i/mg/8/e0/5a8c5b10de245/portrait_medium.jpg","issueCount":11,"issues":[{"id":11945,"title":"Vampire Tales (1973) #11","issueNumber":11.0,"resourceURI":"http://gateway.marvel.com/v1/public/comics/11945","date":"1975-06-10T00:00:00-0400","price":9.99,"thumbnail":"http://i.annihil.us/u/prod/marvel/i/mg/6/f0/56fd7e649f040/portrait_medium.jpg"},{"id":11944,"title":"Vampire Tales (1973) #10","issueNumber":10.0,"resourceURI":"http://gateway.marvel.com/v1/public/comics/11944","date":"1975-04-10T00:00:00-0400","price":9.99,"thumbnail":"http://i.annihil.us/u/prod/marvel/i/mg/d/20/56fd7e77b3c5e/portrait_medium.jpg"},{"id":11953,"title":"Vampire Tales (1973) #9","issueNumber":9.0,"resourceURI":"http://gateway.marvel.com/v1/public/comics/11953","date":"1975-02-10T00:00:00-0500","price":9.99,"thumbnail":"http://i.annihil.us/u/prod/marvel/i/mg/c/f0/56fd7e37c4f2d/portrait_medium.jpg"},{"id":11952,"title":"Vampire Tales (1973) #8","issueNumber":8.0,"resourceURI":"http://gateway.marvel.com/v1/public/comics/11952","date":"1974-12-10T00:00:00-0500","price":9.99,"thumbnail":"http://i.annihil.us/u/prod/marvel/i/mg/7/30/56fd80d89d507/portrait_medium.jpg"},{"id":11951,"title":"Vampire Tales (1973) #7","issueNumber":7.0,"resourceURI":"http://gateway.marvel.com/v1/public/comics/11951","date":"1974-10-10T00:00:00-0400","price":9.99,"thumbnail":"http://i.annihil.us/u/prod/marvel/i/mg/d/10/56fd80f09fe8a/portrait_medium.jpg"},{"id":11950,"title":"Vampire Tales (1973) #6","issueNumber":6.0,"resourceURI":"http://gateway.marvel.com/v1/public/comics/11950","date":"1974-08-10T00:00:00-0400","price":9.99,"thumbnail":"http://i.annihil.us/u/prod/marvel/i/mg/a/40/56fd7df466a66/portrait_medium.jpg"},{"id":11949,"title":"Vampire Tales (1973) #5","issueNumber":5.0,"resourceURI":"http://gateway.marvel.com/v1/public/comics/11949","date":"1974-06-10T00:00:00-0400","price":9.99,"thumbnail":"http://i.annihil.us/u/prod/marvel/i/mg/c/90/56fd7e26ed14a/portrait_medium.jpg"},{"id":11948,"title":"Vampire Tales (1973) #4","issueNumber":4.0,"resourceURI":"http://gateway.marvel.com/v1/public/comics/11948","date":"1974-04-10T00:00:00-0400","price":9.99,"thumbnail":"http://i.annihil.us/u/prod/marvel/i/mg/6/60/56fd8041b650f/portrait_medium.jpg"},{"id":11947,"title":"Vampire Tales (1973) #3","issueNumber":3.0,"resourceURI":"http://gateway.marvel.com/v1/public/comics/11947","date":"1974-02-10T00:00:00-0400","price":9.99,"thumbnail":"http://i.annihil.us/u/prod/marvel/i/mg/e/f0/56fd803ae2aad/portrait_medium.jpg"},{"id":11946,"title":"Vampire Tales (1973) #2","issueNumber":2.0,"resourceURI":"http://gateway.marvel.com/v1/public/comics/11946","date":"1973-10-10T00:00:00-0400","price":9.99,"thumbnail":"http://i.annihil.us/u/prod/marvel/i/mg/9/a0/56fd8073ec8b0/portrait_medium.jpg"},{"id":11943,"title":"Vampire Tales (1973) #1","issueNumber":1.0,"resourceURI":"http://gateway.marvel.com/v1/public/comics/11943","date":"1973-06-10T00:00:00-0400","price":9.99,"thumbnail":"http://i.annihil.us/u/prod/marvel/i/mg/a/10/56fd34f9c72c6/portrait_medium.jpg"}]}