{"id":"21003","title":"Damage Control (1989)","description":"","resourceURI":"http://gateway.marvel.com/v1/public/series/21003","startYear":1989,"endYear":1989,"thumbnail":"http://i.annihil.us/u/prod/marvel/i/mg/9/70/57e584b711dad/portrait_medium.jpg","issueCount":4,"issues":[{"id":57671,"title":"Damage Control (1989) #4","issueNumber":4.0,"resourceURI":"http://gateway.marvel.com/v1/public/comics/57671","date":"1989-08-01T00:00:00-0400","price":0.0,"thumbnail":"http://i.annihil.us/u/prod/marvel/i/mg/4/40/57e588311e9c7/portrait_medium.jpg"},{"id":57670,"title":"Damage Control (1989) #3","issueNumber":3.0,"resourceURI":"http://gateway.marvel.com/v1/public/comics/57670","date":"1989-07-01T00:00:00-0400","price":0.0,"thumbnail":"http://i.annihil.us/u/prod/marvel/i/mg/1/a0/57e58746e7383/portrait_medium.jpg"},{"id":57669,"title":"Damage Control (1989) #2","issueNumber":2.0,"resourceURI":"http://gateway.marvel.com/v1/public/comics/57669","date":"1989-06-01T00:00:00-0400","price":0.0,"thumbnail":"http://i.annihil.us/u/prod/marvel/i/mg/6/f0/57e585d1d3e55/portrait_medium.jpg"},{"id":57668,"title":"Damage Control (1989) #1","issueNumber":1.0,"resourceURI":"http://gateway.marvel.com/v1/public/comics/57668","date":"1989-05-01T00:00:00-0400","price":0.0,"thumbnail":"http://i.annihil.us/u/prod/marvel/i/mg/9/70/57e584b711dad/portrait_medium.jpg"}]}