{"id":"2293","title":"Speedball (1988 - 1989)","description":"","resourceURI":"http://gateway.marvel.com/v1/public/series/2293","startYear":1988,"endYear":1989,"thumbnail":"http://i.annihil.us/u/prod/marvel/i/mg/c/40/5a8f26e5ea50b/portrait_medium.jpg","issueCount":10,"issues":[{"id":15283,"title":"Speedball (1988) #10","issueNumber":10.0,"resourceURI":"http://gateway.marvel.com/v1/public/comics/15283","date":"1989-06-10T00:00:00-0400","price":0.75,"thumbnail":"http://i.annihil.us/u/prod/marvel/i/mg/b/40/image_not_available/portrait_medium.jpg"},{"id":15291,"title":"Speedball (1988) #9","issueNumber":9.0,"resourceURI":"http://gateway.marvel.com/v1/public/comics/15291","date":"1989-05-10T00:00:00-0400","price":0.75,"thumbnail":"http://i.annihil.us/u/prod/marvel/i/mg/b/40/image_not_available/portrait_medium.jpg"},{"id":15290,"title":"Speedball (1988) #8","issueNumber":8.0,"resourceURI":"http://gateway.marvel.com/v1/public/comics/15290","date":"1989-04-10T00:00:00-0400","price":0.75,"thumbnail":"http://i.annihil.us/u/prod/marvel/i/mg/b/40/image_not_available/portrait_medium.jpg"},{"id":15289,"title":"Speedball (1988) #7","issueNumber":7.0,"resourceURI":"http://gateway.marvel.com/v1/public/comics/15289","date":"1989-03-10T00:00:00-0500","price":0.75,"thumbnail":"http://i.annihil.us/u/prod/marvel/i/mg/b/40/image_not_available/portrait_medium.jpg"},{"id":15288,"title":"Speedball (1988) #6","issueNumber":6.0,"resourceURI":"http://gateway.marvel.com/v1/public/comics/15288","date":"1989-02-10T00:00:00-0500","price":0.75,"thumbnail":"http://i.annihil.us/u/prod/marvel/i/mg/c/60/50ad2d94e5f6b/portrait_medium.jpg"},{"id":15287,"title":"Speedball (1988) #5","issueNumber":5.0,"resourceURI":"http://gateway.marvel.com/v1/public/comics/15287","date":"1989-01-10T00:00:00-0500","price":0.75,"thumbnail":"http://i.annihil.us/u/prod/marvel/i/mg/b/40/image_not_available/portrait_medium.jpg"},{"id":15286,"title":"Speedball (1988) #4","issueNumber":4.0,"resourceURI":"http://gateway.marvel.com/v1/public/comics/15286","date":"1988-12-10T00:00:00-0500","price":0.75,"thumbnail":"http://i.annihil.us/u/prod/marvel/i/mg/b/40/image_not_available/portrait_medium.jpg"},{"id":15285,"title":"Speedball (1988) #3","issueNumber":3.0,"resourceURI":"http://gateway.marvel.com/v1/public/comics/15285","date":"1988-11-10T00:00:00-0500","price":0.75,"thumbnail":"http://i.annihil.us/u/prod/marvel/i/mg/b/40/image_not_available/portrait_medium.jpg"},{"id":15284,"title":"Speedball (1988) #2","issueNumber":2.0,"resourceURI":"http://gateway.marvel.com/v1/public/comics/15284","date":"1988-10-10T00:00:00-0400","price":0.75,"thumbnail":"http://i.annihil.us/u/prod/marvel/i/mg/b/40/image_not_available/portrait_medium.jpg"},{"id":15282,"title":"Speedball (1988) #1","issueNumber":1.0,"resourceURI":"http://gateway.marvel.com/v1/public/comics/15282","date":"1988-09-10T00:00:00-0400","price":0.75,"thumbnail":"http://i.annihil.us/u/prod/marvel/i/mg/3/70/4bc4690d27931/portrait_medium.jpg"}]}