{"id":"23996","title":"Marc Spector: Moon Knight (1989 - 1994)","description":"","resourceURI":"http://gateway.marvel.com/v1/public/series/23996","startYear":1989,"endYear":1994,"thumbnail":"http://i.annihil.us/u/prod/marvel/i/mg/5/c0/5a306f2a87a30/portrait_medium.jpg","issueCount":3,"issues":[{"id":66178,"title":"Marc Spector: Moon Knight (1989) #10","issueNumber":10.0,"resourceURI":"http://gateway.marvel.com/v1/public/comics/66178","date":"1990-01-01T00:00:00-0500","price":0.0,"thumbnail":"http://i.annihil.us/u/prod/marvel/i/mg/6/80/5a306f45e27c8/portrait_medium.jpg"},{"id":66177,"title":"Marc Spector: Moon Knight (1989) #9","issueNumber":9.0,"resourceURI":"http://gateway.marvel.com/v1/public/comics/66177","date":"1989-12-15T00:00:00-0500","price":0.0,"thumbnail":"http://i.annihil.us/u/prod/marvel/i/mg/5/03/5a307066255d8/portrait_medium.jpg"},{"id":66176,"title":"Marc Spector: Moon Knight (1989) #8","issueNumber":8.0,"resourceURI":"http://gateway.marvel.com/v1/public/comics/66176","date":"1989-12-01T00:00:00-0500","price":0.0,"thumbnail":"http://i.annihil.us/u/prod/marvel/i/mg/5/c0/5a306f2a87a30/portrait_medium.jpg"}]}